[
  {
    "Type": "游艺设备",
    "Devices": [
      {
        "Name": "音符跳跳球",
        "DeviceCategory": "游艺机",
        "ApprovalNumber": "粤游艺审〔2024〕1187号",
        "SupervisionPhone": "12318",
        "Link": "https://sh.gegia.cn/#/scanningView?id=9420"
      },
      {
        "Name": "洛丽单剪（粉色）",
        "DeviceCategory": "游艺机",
        "ApprovalNumber": "粤游艺审〔2024〕899号",
        "SupervisionPhone": "12318",
        "Link": "https://sh.gegia.cn/#/scanningView?id=9687"
      },
      {
        "Name": "洛丽单剪（红色）–A",
        "DeviceCategory": "游艺机",
        "ApprovalNumber": "粤游艺审〔2024〕900号",
        "SupervisionPhone": "12318",
        "Link": "https://sh.gegia.cn/#/scanningView?id=9688"
      },
      {
        "Name": "极速摩托3",
        "DeviceCategory": "游艺机",
        "ApprovalNumber": "粤游审【2017】A758号",
        "SupervisionPhone": "12318",
        "Link": "https://sh.gegia.cn/#/scanningView?id=104"
      },
      {
        "Name": "抓抓乐Plus",
        "DeviceCategory": "游艺机",
        "ApprovalNumber": "粤游艺审〔2024〕169号",
        "SupervisionPhone": "12318",
        "Link": "https://sh.gegia.cn/#/scanningView?id=8814"
      },
      {
        "Name": "疯狂曲棍X",
        "DeviceCategory": "游艺机",
        "ApprovalNumber": "粤游艺审〔2024〕2号",
        "SupervisionPhone": "12318",
        "Link": "https://sh.gegia.cn/#/scanningView?id=8609"
      },
      {
        "Name": "天空之城专版A",
        "DeviceCategory": "游艺机",
        "ApprovalNumber": "粤游艺审〔2024〕1号",
        "SupervisionPhone": "12318",
        "Link": "https://sh.gegia.cn/#/scanningView?id=8706"
      },
      {
        "Name": "天空之环",
        "DeviceCategory": "游艺机",
        "ApprovalNumber": "粤游艺审〔2023〕724号",
        "SupervisionPhone": "12318",
        "Link": "https://sh.gegia.cn/#/scanningView?id=6893"
      },
      {
        "Name": "黑玫瑰-超大",
        "DeviceCategory": "游艺机",
        "ApprovalNumber": "粤游艺审〔2023〕723号",
        "SupervisionPhone": "12318",
        "Link": "https://sh.gegia.cn/#/scanningView?id=7532"
      },
      {
        "Name": "疯狂曲棍S",
        "DeviceCategory": "游艺机",
        "ApprovalNumber": "粤游艺审〔2023〕720号",
        "SupervisionPhone": "12318",
        "Link": "https://sh.gegia.cn/#/scanningView?id=8043"
      },
      {
        "Name": "黑玫瑰-迷你四人",
        "DeviceCategory": "游艺机",
        "ApprovalNumber": "粤游艺审〔2023〕722号",
        "SupervisionPhone": "12318",
        "Link": "https://sh.gegia.cn/#/scanningView?id=8038"
      },
      {
        "Name": "幻境神枪",
        "DeviceCategory": "游艺机",
        "ApprovalNumber": "粤游艺审〔2023〕721号",
        "SupervisionPhone": "12318",
        "Link": "https://sh.gegia.cn/#/scanningView?id=8042"
      },
      {
        "Name": "黑玫瑰-中岛机",
        "DeviceCategory": "游艺机",
        "ApprovalNumber": "粤游艺审〔2023〕343号",
        "SupervisionPhone": "12318",
        "Link": "https://sh.gegia.cn/#/scanningView?id=7524"
      },
      {
        "Name": "黑玫瑰-盲盒机",
        "DeviceCategory": "游艺机",
        "ApprovalNumber": "粤游艺审〔2023〕342号",
        "SupervisionPhone": "12318",
        "Link": "https://sh.gegia.cn/#/scanningView?id=7525"
      },
      {
        "Name": "夹多多-L",
        "DeviceCategory": "游艺机",
        "ApprovalNumber": "粤游艺审〔2023〕346号",
        "SupervisionPhone": "12318",
        "Link": "https://sh.gegia.cn/#/scanningView?id=7427"
      },
      {
        "Name": "夹多多-M",
        "DeviceCategory": "游艺机",
        "ApprovalNumber": "粤游艺审〔2023〕345号",
        "SupervisionPhone": "12318",
        "Link": "https://sh.gegia.cn/#/scanningView?id=7522"
      },
      {
        "Name": "恐龙帝国",
        "DeviceCategory": "游艺机",
        "ApprovalNumber": "粤游艺审〔2023〕157号",
        "SupervisionPhone": "12318",
        "Link": "https://sh.gegia.cn/#/scanningView?id=7000"
      },
      {
        "Name": "洛丽夺宝",
        "DeviceCategory": "游艺机",
        "ApprovalNumber": "粤游艺审〔2023〕158号",
        "SupervisionPhone": "12318",
        "Link": "https://sh.gegia.cn/#/scanningView?id=6894"
      },
      {
        "Name": "洛丽潮品汇",
        "DeviceCategory": "游艺机",
        "ApprovalNumber": "粤游艺审〔2023〕159号",
        "SupervisionPhone": "12318",
        "Link": "https://sh.gegia.cn/#/scanningView?id=6764"
      },
      {
        "Name": "抖盒",
        "DeviceCategory": "游艺机",
        "ApprovalNumber": "粤游艺审〔2023〕156号",
        "SupervisionPhone": "12318",
        "Link": "https://sh.gegia.cn/#/scanningView?id=7240"
      },
      {
        "Name": "天空之城潮品汇",
        "DeviceCategory": "游艺机",
        "ApprovalNumber": "粤游艺审〔2023〕160号",
        "SupervisionPhone": "12318",
        "Link": "https://sh.gegia.cn/#/scanningView?id=6597"
      },
      {
        "Name": "大玩家-如意-MB",
        "DeviceCategory": "游艺机",
        "ApprovalNumber": "粤游艺审〔2023〕4号",
        "SupervisionPhone": "12318",
        "Link": "https://sh.gegia.cn/#/scanningView?id=6165"
      },
      {
        "Name": "洛丽单人-A",
        "DeviceCategory": "游艺机",
        "ApprovalNumber": "粤游艺审〔2023〕1号",
        "SupervisionPhone": "12318",
        "Link": "https://sh.gegia.cn/#/scanningView?id=6596"
      },
      {
        "Name": "天空之城超大",
        "DeviceCategory": "游艺机",
        "ApprovalNumber": "粤游艺审〔2023〕2号",
        "SupervisionPhone": "12318",
        "Link": "https://sh.gegia.cn/#/scanningView?id=6567"
      },
      {
        "Name": "天空之城四人迷你",
        "DeviceCategory": "游艺机",
        "ApprovalNumber": "粤游艺审〔2023〕3号",
        "SupervisionPhone": "12318",
        "Link": "https://sh.gegia.cn/#/scanningView?id=6566"
      },
      {
        "Name": "疯狂曲棍2",
        "DeviceCategory": "游艺机",
        "ApprovalNumber": "粤游艺审〔2022〕677号",
        "SupervisionPhone": "12318",
        "Link": "https://sh.gegia.cn/#/scanningView?id=6083"
      },
      {
        "Name": "大玩家-玲珑-B",
        "DeviceCategory": "游艺机",
        "ApprovalNumber": "粤游艺审〔2022〕672号",
        "SupervisionPhone": "12318",
        "Link": "https://sh.gegia.cn/#/scanningView?id=6191"
      },
      {
        "Name": "二哈勿扰",
        "DeviceCategory": "游艺机",
        "ApprovalNumber": "粤游艺审〔2022〕673号",
        "SupervisionPhone": "12318",
        "Link": "https://sh.gegia.cn/#/scanningView?id=6190"
      },
      {
        "Name": "大玩家-玲珑-FB",
        "DeviceCategory": "游艺机",
        "ApprovalNumber": "粤游艺审〔2022〕671号",
        "SupervisionPhone": "12318",
        "Link": "https://sh.gegia.cn/#/scanningView?id=6192"
      },
      {
        "Name": "洛丽单人",
        "DeviceCategory": "游艺机",
        "ApprovalNumber": "粤游艺审〔2022〕676号",
        "SupervisionPhone": "12318",
        "Link": "https://sh.gegia.cn/#/scanningView?id=6162"
      },
      {
        "Name": "洛丽元次方",
        "DeviceCategory": "游艺机",
        "ApprovalNumber": "粤游艺审〔2022〕674号",
        "SupervisionPhone": "12318",
        "Link": "https://sh.gegia.cn/#/scanningView?id=6164"
      },
      {
        "Name": "洛丽超大",
        "DeviceCategory": "游艺机",
        "ApprovalNumber": "粤游艺审〔2022〕675号",
        "SupervisionPhone": "12318",
        "Link": "https://sh.gegia.cn/#/scanningView?id=6163"
      },
      {
        "Name": "极速雪摩",
        "DeviceCategory": "游艺机",
        "ApprovalNumber": "粤游艺审〔2022〕313号",
        "SupervisionPhone": "12318",
        "Link": "https://sh.gegia.cn/#/scanningView?id=5368"
      },
      {
        "Name": "神来之手X",
        "DeviceCategory": "游艺机",
        "ApprovalNumber": "粤游艺审〔2022〕52号",
        "SupervisionPhone": "12318",
        "Link": "https://sh.gegia.cn/#/scanningView?id=5211"
      },
      {
        "Name": "天空之城专版",
        "DeviceCategory": "游艺机",
        "ApprovalNumber": "粤游艺审〔2022〕189号",
        "SupervisionPhone": "12318",
        "Link": "https://sh.gegia.cn/#/scanningView?id=5182"
      },
      {
        "Name": "赏金猎手",
        "DeviceCategory": "游艺机",
        "ApprovalNumber": "粤游艺审〔2022〕53号",
        "SupervisionPhone": "12318",
        "Link": "https://sh.gegia.cn/#/scanningView?id=5115"
      },
      {
        "Name": "咔啦酷",
        "DeviceCategory": "游艺机",
        "ApprovalNumber": "粤游艺审〔2021〕999号",
        "SupervisionPhone": "12318",
        "Link": "https://sh.gegia.cn/#/scanningView?id=4971"
      },
      {
        "Name": "PP虎玛丽",
        "DeviceCategory": "游艺机",
        "ApprovalNumber": "粤游艺审〔2021〕1001号",
        "SupervisionPhone": "12318",
        "Link": "https://sh.gegia.cn/#/scanningView?id=3757"
      },
      {
        "Name": "元次方",
        "DeviceCategory": "游艺机",
        "ApprovalNumber": "粤游艺审〔2021〕1000号",
        "SupervisionPhone": "12318",
        "Link": "https://sh.gegia.cn/#/scanningView?id=4970"
      },
      {
        "Name": "神来之手（蓝色）",
        "DeviceCategory": "游艺机",
        "ApprovalNumber": "粤游艺审〔2021〕1002号",
        "SupervisionPhone": "12318",
        "Link": "https://sh.gegia.cn/#/scanningView?id=3756"
      },
      {
        "Name": "火焰西游",
        "DeviceCategory": "游艺机",
        "ApprovalNumber": "粤游艺审〔2021〕793号",
        "SupervisionPhone": "12318",
        "Link": "https://sh.gegia.cn/#/scanningView?id=3020"
      },
      {
        "Name": "魔盒传说",
        "DeviceCategory": "游艺机",
        "ApprovalNumber": "粤游艺审〔2021〕792号",
        "SupervisionPhone": "12318",
        "Link": "https://sh.gegia.cn/#/scanningView?id=3692"
      },
      {
        "Name": "火焰西游A",
        "DeviceCategory": "游艺机",
        "ApprovalNumber": "粤游艺审〔2021〕791号",
        "SupervisionPhone": "12318",
        "Link": "https://sh.gegia.cn/#/scanningView?id=3781"
      },
      {
        "Name": "神来之手S",
        "DeviceCategory": "游艺机",
        "ApprovalNumber": "粤游艺审〔2021〕366号",
        "SupervisionPhone": "12318",
        "Link": "https://sh.gegia.cn/#/scanningView?id=3923"
      },
      {
        "Name": "PP虎5X",
        "DeviceCategory": "游艺机",
        "ApprovalNumber": "粤游艺审〔2021〕365号",
        "SupervisionPhone": "12318",
        "Link": "https://sh.gegia.cn/#/scanningView?id=3755"
      },
      {
        "Name": "PP虎双人多剪",
        "DeviceCategory": "游艺机",
        "ApprovalNumber": "粤游艺审〔2021〕364号",
        "SupervisionPhone": "12318",
        "Link": "https://sh.gegia.cn/#/scanningView?id=3754"
      },
      {
        "Name": "包子铺",
        "DeviceCategory": "游艺机",
        "ApprovalNumber": "粤游艺审〔2021〕48号",
        "SupervisionPhone": "12318",
        "Link": "https://sh.gegia.cn/#/scanningView?id=3018"
      },
      {
        "Name": "潮品汇",
        "DeviceCategory": "游艺机",
        "ApprovalNumber": "粤游艺审〔2021〕53号",
        "SupervisionPhone": "12318",
        "Link": "https://sh.gegia.cn/#/scanningView?id=3542"
      },
      {
        "Name": "极速摩托S",
        "DeviceCategory": "游艺机",
        "ApprovalNumber": "粤游艺审〔2021〕50号",
        "SupervisionPhone": "12318",
        "Link": "https://sh.gegia.cn/#/scanningView?id=3349"
      },
      {
        "Name": "PP虎迷你2人",
        "DeviceCategory": "游艺机",
        "ApprovalNumber": "粤游艺审〔2021〕52号",
        "SupervisionPhone": "12318",
        "Link": "https://sh.gegia.cn/#/scanningView?id=3379"
      },
      {
        "Name": "命运战姬",
        "DeviceCategory": "游艺机",
        "ApprovalNumber": "粤游艺审〔2021〕49号",
        "SupervisionPhone": "12318",
        "Link": "https://sh.gegia.cn/#/scanningView?id=3019"
      },
      {
        "Name": "PP虎迷你4人",
        "DeviceCategory": "游艺机",
        "ApprovalNumber": "粤游艺审〔2021〕51号",
        "SupervisionPhone": "12318",
        "Link": "https://sh.gegia.cn/#/scanningView?id=3378"
      },
      {
        "Name": "PP虎单剪",
        "DeviceCategory": "游艺机",
        "ApprovalNumber": "粤游审〔2020〕324号",
        "SupervisionPhone": "12318",
        "Link": "https://sh.gegia.cn/#/scanningView?id=3085"
      },
      {
        "Name": "PP虎超大",
        "DeviceCategory": "游艺机",
        "ApprovalNumber": "粤游审〔2020〕323号",
        "SupervisionPhone": "12318",
        "Link": "https://sh.gegia.cn/#/scanningView?id=3084"
      },
      {
        "Name": "派对列车",
        "DeviceCategory": "游艺机",
        "ApprovalNumber": "粤游审〔2020〕321号",
        "SupervisionPhone": "12318",
        "Link": "https://sh.gegia.cn/#/scanningView?id=2137"
      },
      {
        "Name": "PP虎单人S",
        "DeviceCategory": "游艺机",
        "ApprovalNumber": "粤游审〔2020〕327号",
        "SupervisionPhone": "12318",
        "Link": "https://sh.gegia.cn/#/scanningView?id=3127"
      },
      {
        "Name": "PP虎迷你",
        "DeviceCategory": "游艺机",
        "ApprovalNumber": "粤游审〔2020〕326号",
        "SupervisionPhone": "12318",
        "Link": "https://sh.gegia.cn/#/scanningView?id=3087"
      },
      {
        "Name": "PP虎单人",
        "DeviceCategory": "游艺机",
        "ApprovalNumber": "粤游审〔2020〕322号",
        "SupervisionPhone": "12318",
        "Link": "https://sh.gegia.cn/#/scanningView?id=3023"
      },
      {
        "Name": "宝贝熊2",
        "DeviceCategory": "游艺机",
        "ApprovalNumber": "粤游审〔2020〕328号",
        "SupervisionPhone": "12318",
        "Link": "https://sh.gegia.cn/#/scanningView?id=3193"
      },
      {
        "Name": "PP虎双人",
        "DeviceCategory": "游艺机",
        "ApprovalNumber": "粤游审〔2020〕325号",
        "SupervisionPhone": "12318",
        "Link": "https://sh.gegia.cn/#/scanningView?id=3086"
      },
      {
        "Name": "神来之手迷你",
        "DeviceCategory": "游艺机",
        "ApprovalNumber": "粤游审〔2020〕128号",
        "SupervisionPhone": "12318",
        "Link": "https://sh.gegia.cn/#/scanningView?id=2837"
      },
      {
        "Name": "铁甲曲棍",
        "DeviceCategory": "游艺机",
        "ApprovalNumber": "粤游审〔2020〕127号",
        "SupervisionPhone": "12318",
        "Link": "https://sh.gegia.cn/#/scanningView?id=2836"
      },
      {
        "Name": "星球坠落",
        "DeviceCategory": "游艺机",
        "ApprovalNumber": "粤游审〔2020〕126号",
        "SupervisionPhone": "12318",
        "Link": "https://sh.gegia.cn/#/scanningView?id=2363"
      },
      {
        "Name": "大玩家疯狂曲棍",
        "DeviceCategory": "游艺机",
        "ApprovalNumber": "粤游审〔2020〕20号",
        "SupervisionPhone": "12318",
        "Link": "https://sh.gegia.cn/#/scanningView?id=2656"
      },
      {
        "Name": "守护者联盟（新版）",
        "DeviceCategory": "游艺机",
        "ApprovalNumber": "粤游审〔2020〕18号",
        "SupervisionPhone": "12318",
        "Link": "https://sh.gegia.cn/#/scanningView?id=2161"
      },
      {
        "Name": "曲棍球棒恰恰",
        "DeviceCategory": "游艺机",
        "ApprovalNumber": "粤游审〔2020〕21号",
        "SupervisionPhone": "12318",
        "Link": "https://sh.gegia.cn/#/scanningView?id=2657"
      },
      {
        "Name": "守护者联盟",
        "DeviceCategory": "游艺机",
        "ApprovalNumber": "粤游审〔2019〕A514号",
        "SupervisionPhone": "12318",
        "Link": "https://sh.gegia.cn/#/scanningView?id=1813"
      },
      {
        "Name": "疯狂曲棍2019",
        "DeviceCategory": "游艺机",
        "ApprovalNumber": "粤游审〔2019〕A517号",
        "SupervisionPhone": "12318",
        "Link": "https://sh.gegia.cn/#/scanningView?id=2406"
      },
      {
        "Name": "守护者联盟（双人）",
        "DeviceCategory": "游艺机",
        "ApprovalNumber": "粤游审〔2019〕A516号",
        "SupervisionPhone": "12318",
        "Link": "https://sh.gegia.cn/#/scanningView?id=2347"
      },
      {
        "Name": "石器达人（双人版）",
        "DeviceCategory": "游艺机",
        "ApprovalNumber": "粤游审〔2019〕A515号",
        "SupervisionPhone": "12318",
        "Link": "https://sh.gegia.cn/#/scanningView?id=2129"
      },
      {
        "Name": "大玩家-畅剪-B",
        "DeviceCategory": "游艺机",
        "ApprovalNumber": "粤游审〔2019〕A362号",
        "SupervisionPhone": "12318",
        "Link": "https://sh.gegia.cn/#/scanningView?id=2128"
      },
      {
        "Name": "大玩家-如意-B ",
        "DeviceCategory": "游艺机",
        "ApprovalNumber": "粤游审〔2019〕A361号",
        "SupervisionPhone": "12318",
        "Link": "https://sh.gegia.cn/#/scanningView?id=2127"
      },
      {
        "Name": "神来之手",
        "DeviceCategory": "游艺机",
        "ApprovalNumber": "粤游审〔2019〕A159号",
        "SupervisionPhone": "12318",
        "Link": "https://sh.gegia.cn/#/scanningView?id=1603"
      },
      {
        "Name": "PP虎Ⅳ (粉色、黑色)",
        "DeviceCategory": "游艺机",
        "ApprovalNumber": "粤游审〔2019〕A160号",
        "SupervisionPhone": "12318",
        "Link": "https://sh.gegia.cn/#/scanningView?id=1790"
      },
      {
        "Name": "剪吧（粉色、黑色）",
        "DeviceCategory": "游艺机",
        "ApprovalNumber": "粤游审〔2019〕A162号",
        "SupervisionPhone": "12318",
        "Link": "https://sh.gegia.cn/#/scanningView?id=1810"
      },
      {
        "Name": "大玩家2019娃娃机",
        "DeviceCategory": "游艺机",
        "ApprovalNumber": "粤游审〔2019〕A163号",
        "SupervisionPhone": "12318",
        "Link": "https://sh.gegia.cn/#/scanningView?id=1857"
      },
      {
        "Name": "极速摩托3DX",
        "DeviceCategory": "游艺机",
        "ApprovalNumber": "粤游审〔2019〕A161号",
        "SupervisionPhone": "12318",
        "Link": "https://sh.gegia.cn/#/scanningView?id=1791"
      },
      {
        "Name": "巨无霸2",
        "DeviceCategory": "游艺机",
        "ApprovalNumber": "粤游审【2019】A020号",
        "SupervisionPhone": "12318",
        "Link": "https://sh.gegia.cn/#/scanningView?id=1556"
      },
      {
        "Name": "欢乐夹夹乐（礼品版）",
        "DeviceCategory": "游艺机",
        "ApprovalNumber": "粤游审【2019】A021号",
        "SupervisionPhone": "12318",
        "Link": "https://sh.gegia.cn/#/scanningView?id=1557"
      },
      {
        "Name": "城堡历险（双人版）",
        "DeviceCategory": "游艺机",
        "ApprovalNumber": "粤游审〔2018〕A846号",
        "SupervisionPhone": "12318",
        "Link": "https://sh.gegia.cn/#/scanningView?id=1368"
      },
      {
        "Name": "四季之恋（单人plus版）",
        "DeviceCategory": "游艺机",
        "ApprovalNumber": "粤游审〔2018〕A845号",
        "SupervisionPhone": "12318",
        "Link": "https://sh.gegia.cn/#/scanningView?id=1134"
      },
      {
        "Name": "抛球达人",
        "DeviceCategory": "游艺机",
        "ApprovalNumber": "粤游审〔2018〕A847号",
        "SupervisionPhone": "12318",
        "Link": "https://sh.gegia.cn/#/scanningView?id=1369"
      },
      {
        "Name": "全民吃鱼豪华版",
        "DeviceCategory": "游艺机",
        "ApprovalNumber": "粤游审〔2018〕A586号",
        "SupervisionPhone": "12318",
        "Link": "https://sh.gegia.cn/#/scanningView?id=720"
      },
      {
        "Name": "PP虎列车(单机版)",
        "DeviceCategory": "游艺机",
        "ApprovalNumber": "粤游审〔2018〕A592号",
        "SupervisionPhone": "12318",
        "Link": "https://sh.gegia.cn/#/scanningView?id=917"
      },
      {
        "Name": "敲击大冒险4",
        "DeviceCategory": "游艺机",
        "ApprovalNumber": "粤游审〔2018〕A595号",
        "SupervisionPhone": "12318",
        "Link": "https://sh.gegia.cn/#/scanningView?id=1124"
      },
      {
        "Name": "黄金时刻2",
        "DeviceCategory": "游艺机",
        "ApprovalNumber": "粤游审〔2018〕A585号",
        "SupervisionPhone": "12318",
        "Link": "https://sh.gegia.cn/#/scanningView?id=480"
      },
      {
        "Name": "四季之恋(单机版)",
        "DeviceCategory": "游艺机",
        "ApprovalNumber": "粤游审〔2018〕A593号",
        "SupervisionPhone": "12318",
        "Link": "https://sh.gegia.cn/#/scanningView?id=936"
      },
      {
        "Name": "超强吸力",
        "DeviceCategory": "游艺机",
        "ApprovalNumber": "粤游审〔2018〕A594号",
        "SupervisionPhone": "12318",
        "Link": "https://sh.gegia.cn/#/scanningView?id=1070"
      },
      {
        "Name": "星座连萌（粉、绿）",
        "DeviceCategory": "游艺机",
        "ApprovalNumber": "粤游审〔2018〕A588号",
        "SupervisionPhone": "12318",
        "Link": "https://sh.gegia.cn/#/scanningView?id=762"
      },
      {
        "Name": "城堡历险",
        "DeviceCategory": "游艺机",
        "ApprovalNumber": "粤游审〔2018〕A589号",
        "SupervisionPhone": "12318",
        "Link": "https://sh.gegia.cn/#/scanningView?id=763"
      },
      {
        "Name": "海盗乐翻天2",
        "DeviceCategory": "游艺机",
        "ApprovalNumber": "粤游审〔2018〕A587号",
        "SupervisionPhone": "12318",
        "Link": "https://sh.gegia.cn/#/scanningView?id=737"
      },
      {
        "Name": "四季之恋",
        "DeviceCategory": "游艺机",
        "ApprovalNumber": "粤游审〔2018〕A584号",
        "SupervisionPhone": "12318",
        "Link": "https://sh.gegia.cn/#/scanningView?id=475"
      },
      {
        "Name": "星座派对（粉、绿）",
        "DeviceCategory": "游艺机",
        "ApprovalNumber": "粤游审〔2018〕A591号",
        "SupervisionPhone": "12318",
        "Link": "https://sh.gegia.cn/#/scanningView?id=864"
      },
      {
        "Name": "欢乐夹夹乐",
        "DeviceCategory": "游艺机",
        "ApprovalNumber": "粤游审〔2018〕A590号",
        "SupervisionPhone": "12318",
        "Link": "https://sh.gegia.cn/#/scanningView?id=863"
      },
      {
        "Name": "全民吃鱼",
        "DeviceCategory": "游艺机",
        "ApprovalNumber": "粤游审〔2018〕A264号",
        "SupervisionPhone": "12318",
        "Link": "https://sh.gegia.cn/#/scanningView?id=442"
      },
      {
        "Name": "龙飞凤舞",
        "DeviceCategory": "游艺机",
        "ApprovalNumber": "粤游审〔2018〕A263号",
        "SupervisionPhone": "12318",
        "Link": "https://sh.gegia.cn/#/scanningView?id=434"
      },
      {
        "Name": "PP虎2S",
        "DeviceCategory": "游艺机",
        "ApprovalNumber": "粤游审〔2018〕A018号",
        "SupervisionPhone": "12318",
        "Link": "https://sh.gegia.cn/#/scanningView?id=his_1542"
      },
      {
        "Name": "幸运神箭（木框版）",
        "DeviceCategory": "游艺机",
        "ApprovalNumber": "粤游审〔2017〕A210号",
        "SupervisionPhone": "12318",
        "Link": "https://sh.gegia.cn/#/scanningView?id=his_291"
      },
      {
        "Name": "PP虎3",
        "DeviceCategory": "游艺机",
        "ApprovalNumber": "粤游审〔2017〕A445号",
        "SupervisionPhone": "12318",
        "Link": "https://sh.gegia.cn/#/scanningView?id=his_537"
      },
      {
        "Name": "气球保卫战",
        "DeviceCategory": "游艺机",
        "ApprovalNumber": "粤游审〔2017〕A083号",
        "SupervisionPhone": "12318",
        "Link": "https://sh.gegia.cn/#/scanningView?id=his_89"
      },
      {
        "Name": "银河世纪",
        "DeviceCategory": "游艺机",
        "ApprovalNumber": "粤游审〔2017〕A087号",
        "SupervisionPhone": "12318",
        "Link": "https://sh.gegia.cn/#/scanningView?id=his_93"
      },
      {
        "Name": "时来运转",
        "DeviceCategory": "游艺机",
        "ApprovalNumber": "粤游审〔2017〕A209号",
        "SupervisionPhone": "12318",
        "Link": "https://sh.gegia.cn/#/scanningView?id=his_290"
      },
      {
        "Name": "全民射绳",
        "DeviceCategory": "游艺机",
        "ApprovalNumber": "粤游审〔2017〕A444号",
        "SupervisionPhone": "12318",
        "Link": "https://sh.gegia.cn/#/scanningView?id=his_536"
      },
      {
        "Name": "种树达人",
        "DeviceCategory": "游艺机",
        "ApprovalNumber": "粤游审〔2017〕A082号",
        "SupervisionPhone": "12318",
        "Link": "https://sh.gegia.cn/#/scanningView?id=his_88"
      },
      {
        "Name": "疯狂吊车",
        "DeviceCategory": "游艺机",
        "ApprovalNumber": "粤游审〔2017〕A086号",
        "SupervisionPhone": "12318",
        "Link": "https://sh.gegia.cn/#/scanningView?id=his_92"
      },
      {
        "Name": "布谷鸟2",
        "DeviceCategory": "游艺机",
        "ApprovalNumber": "粤游审〔2017〕A090号",
        "SupervisionPhone": "12318",
        "Link": "https://sh.gegia.cn/#/scanningView?id=his_96"
      },
      {
        "Name": "神奇逃亡",
        "DeviceCategory": "游艺机",
        "ApprovalNumber": "粤游审〔2017〕A208号",
        "SupervisionPhone": "12318",
        "Link": "https://sh.gegia.cn/#/scanningView?id=his_289"
      },
      {
        "Name": "神奇剪刀S",
        "DeviceCategory": "游艺机",
        "ApprovalNumber": "粤游审〔2017〕A443号",
        "SupervisionPhone": "12318",
        "Link": "https://sh.gegia.cn/#/scanningView?id=his_535"
      },
      {
        "Name": "极速摩托3",
        "DeviceCategory": "游艺机",
        "ApprovalNumber": "粤游审〔2017〕A758号",
        "SupervisionPhone": "12318",
        "Link": "https://sh.gegia.cn/#/scanningView?id=his_854"
      },
      {
        "Name": "PP虎家族",
        "DeviceCategory": "游艺机",
        "ApprovalNumber": "粤游审〔2017〕A447号",
        "SupervisionPhone": "12318",
        "Link": "https://sh.gegia.cn/#/scanningView?id=his_539"
      },
      {
        "Name": "双熊宝贝",
        "DeviceCategory": "游艺机",
        "ApprovalNumber": "粤游审〔2017〕A081号",
        "SupervisionPhone": "12318",
        "Link": "https://sh.gegia.cn/#/scanningView?id=his_87"
      },
      {
        "Name": "弹跳高手",
        "DeviceCategory": "游艺机",
        "ApprovalNumber": "粤游审〔2017〕A085号",
        "SupervisionPhone": "12318",
        "Link": "https://sh.gegia.cn/#/scanningView?id=his_91"
      },
      {
        "Name": "橄榄球",
        "DeviceCategory": "游艺机",
        "ApprovalNumber": "粤游审〔2017〕A089号",
        "SupervisionPhone": "12318",
        "Link": "https://sh.gegia.cn/#/scanningView?id=his_95"
      },
      {
        "Name": "神箭达人",
        "DeviceCategory": "游艺机",
        "ApprovalNumber": "粤游审〔2017〕A207号",
        "SupervisionPhone": "12318",
        "Link": "https://sh.gegia.cn/#/scanningView?id=his_288"
      },
      {
        "Name": "冰炫风",
        "DeviceCategory": "游艺机",
        "ApprovalNumber": "粤游审〔2017〕A080号",
        "SupervisionPhone": "12318",
        "Link": "https://sh.gegia.cn/#/scanningView?id=his_86"
      },
      {
        "Name": "降魔猎人",
        "DeviceCategory": "游艺机",
        "ApprovalNumber": "粤游审〔2017〕A084号",
        "SupervisionPhone": "12318",
        "Link": "https://sh.gegia.cn/#/scanningView?id=his_90"
      },
      {
        "Name": "幸运溜溜球",
        "DeviceCategory": "游艺机",
        "ApprovalNumber": "粤游审〔2017〕A088号",
        "SupervisionPhone": "12318",
        "Link": "https://sh.gegia.cn/#/scanningView?id=his_94"
      },
      {
        "Name": "神奇剪刀2-单人",
        "DeviceCategory": "游艺机",
        "ApprovalNumber": "粤游审〔2016〕A209号",
        "SupervisionPhone": "12318",
        "Link": "https://sh.gegia.cn/#/scanningView?id=his_1228"
      },
      {
        "Name": "神奇剪刀2-双人",
        "DeviceCategory": "游艺机",
        "ApprovalNumber": "粤游审〔2016〕A210号",
        "SupervisionPhone": "12318",
        "Link": "https://sh.gegia.cn/#/scanningView?id=his_1229"
      },
      {
        "Name": "疯狂曲棍",
        "DeviceCategory": "游艺机",
        "ApprovalNumber": "粤游审〔2016〕A214号",
        "SupervisionPhone": "12318",
        "Link": "https://sh.gegia.cn/#/scanningView?id=his_1233"
      },
      {
        "Name": "抓抓乐",
        "DeviceCategory": "游艺机",
        "ApprovalNumber": "粤游审〔2016〕A114号",
        "SupervisionPhone": "12318",
        "Link": "https://sh.gegia.cn/#/scanningView?id=his_1133"
      },
      {
        "Name": "吹球机",
        "DeviceCategory": "游艺机",
        "ApprovalNumber": "粤游审〔2016〕A213号",
        "SupervisionPhone": "12318",
        "Link": "https://sh.gegia.cn/#/scanningView?id=his_1232"
      },
      {
        "Name": "相扑激战",
        "DeviceCategory": "游艺机",
        "ApprovalNumber": "粤游审〔2016〕A208号",
        "SupervisionPhone": "12318",
        "Link": "https://sh.gegia.cn/#/scanningView?id=his_1227"
      },
      {
        "Name": "熊猫飞碟球",
        "DeviceCategory": "游艺机",
        "ApprovalNumber": "粤游审〔2016〕A212号",
        "SupervisionPhone": "12318",
        "Link": "https://sh.gegia.cn/#/scanningView?id=his_1231"
      },
      {
        "Name": "迷你PP虎2",
        "DeviceCategory": "游艺机",
        "ApprovalNumber": "粤游审〔2015〕A116号",
        "SupervisionPhone": "12318",
        "Link": "https://sh.gegia.cn/#/scanningView?id=his_1618"
      },
      {
        "Name": "海洋嘉年华平板式",
        "DeviceCategory": "游艺机",
        "ApprovalNumber": "粤游审〔2015〕A115号",
        "SupervisionPhone": "12318",
        "Link": "https://sh.gegia.cn/#/scanningView?id=his_1616"
      },
      {
        "Name": "迷你娃娃机-四人",
        "DeviceCategory": "游艺机",
        "ApprovalNumber": "粤游审〔2015〕A118号",
        "SupervisionPhone": "12318",
        "Link": "https://sh.gegia.cn/#/scanningView?id=his_1620"
      },
      {
        "Name": "闪电博士",
        "DeviceCategory": "游艺机",
        "ApprovalNumber": "粤游审〔2015〕A114号",
        "SupervisionPhone": "12318",
        "Link": "https://sh.gegia.cn/#/scanningView?id=his_1615"
      },
      {
        "Name": "迷你娃娃机-单人",
        "DeviceCategory": "游艺机",
        "ApprovalNumber": "粤游审〔2015〕A117号",
        "SupervisionPhone": "12318",
        "Link": "https://sh.gegia.cn/#/scanningView?id=his_1619"
      },
      {
        "Name": "敲击大冒险2",
        "DeviceCategory": "游艺机",
        "ApprovalNumber": "文游备粤字【2013】27号",
        "SupervisionPhone": "12318",
        "Link": "https://sh.gegia.cn/#/scanningView?id=his_2320"
      },
      {
        "Name": "极速摩托（简易版）",
        "DeviceCategory": "游艺机",
        "ApprovalNumber": "文游备粤字【2012】10号",
        "SupervisionPhone": "12318",
        "Link": "https://sh.gegia.cn/#/scanningView?id=his_2118"
      },
      {
        "Name": "打击恶魔",
        "DeviceCategory": "游艺机",
        "ApprovalNumber": "文游备粤字【2012】113号",
        "SupervisionPhone": "12318",
        "Link": "https://sh.gegia.cn/#/scanningView?id=his_2178"
      },
      {
        "Name": "音炫疯",
        "DeviceCategory": "游艺机",
        "ApprovalNumber": "文游备粤字【2012】117号",
        "SupervisionPhone": "12318",
        "Link": "https://sh.gegia.cn/#/scanningView?id=his_2182"
      },
      {
        "Name": "敲击大冒险3",
        "DeviceCategory": "游艺机",
        "ApprovalNumber": "文游备粤字【2012】9号",
        "SupervisionPhone": "12318",
        "Link": "https://sh.gegia.cn/#/scanningView?id=his_2117"
      },
      {
        "Name": "神奇剪刀",
        "DeviceCategory": "游艺机",
        "ApprovalNumber": "文游备粤字【2012】116号",
        "SupervisionPhone": "12318",
        "Link": "https://sh.gegia.cn/#/scanningView?id=his_2181"
      },
      {
        "Name": "快乐水手",
        "DeviceCategory": "游艺机",
        "ApprovalNumber": "文游备粤字【2012】115号",
        "SupervisionPhone": "12318",
        "Link": "https://sh.gegia.cn/#/scanningView?id=his_2180"
      },
      {
        "Name": "极速摩托（1.5版本）",
        "DeviceCategory": "游艺机",
        "ApprovalNumber": "文游备粤字【2012】11号",
        "SupervisionPhone": "12318",
        "Link": "https://sh.gegia.cn/#/scanningView?id=his_2119"
      },
      {
        "Name": "极速摩托2",
        "DeviceCategory": "游艺机",
        "ApprovalNumber": "文游备粤字【2012】114号",
        "SupervisionPhone": "12318",
        "Link": "https://sh.gegia.cn/#/scanningView?id=his_2179"
      },
      {
        "Name": "兽王拳",
        "DeviceCategory": "游艺机",
        "ApprovalNumber": "文游备粤字【2010】34号",
        "SupervisionPhone": "12318",
        "Link": "https://sh.gegia.cn/#/scanningView?id=his_2081"
      },
      {
        "Name": "星球乐园",
        "DeviceCategory": "游艺机",
        "ApprovalNumber": "文游备粤字【2010】33号",
        "SupervisionPhone": "12318",
        "Link": "https://sh.gegia.cn/#/scanningView?id=his_2080"
      },
      {
        "Name": "拳皇",
        "DeviceCategory": "游艺机",
        "ApprovalNumber": "632",
        "SupervisionPhone": "12318",
        "Link": "https://sh.gegia.cn/#/scanningView?id=his_1758"
      },
      {
        "Name": "敲击大冒险3-欢乐敲敲敲",
        "DeviceCategory": "游艺机",
        "ApprovalNumber": "716",
        "SupervisionPhone": "12318",
        "Link": "https://sh.gegia.cn/#/scanningView?id=his_1546"
      },
      {
        "Name": "魔法城堡",
        "DeviceCategory": "游艺机",
        "ApprovalNumber": "633",
        "SupervisionPhone": "12318",
        "Link": "https://sh.gegia.cn/#/scanningView?id=his_1770"
      },
      {
        "Name": "梵天之塔",
        "DeviceCategory": "游艺机",
        "ApprovalNumber": "634",
        "SupervisionPhone": "12318",
        "Link": "https://sh.gegia.cn/#/scanningView?id=his_2399"
      },
      {
        "Name": "梵天之塔",
        "DeviceCategory": "游艺机",
        "ApprovalNumber": "634",
        "SupervisionPhone": "12318",
        "Link": "https://sh.gegia.cn/#/scanningView?id=his_1782"
      },
      {
        "Name": "幸运娃娃",
        "DeviceCategory": "游艺机",
        "ApprovalNumber": "30",
        "SupervisionPhone": "12318",
        "Link": "https://sh.gegia.cn/#/scanningView?id=his_2234"
      },
      {
        "Name": "星球乐园2",
        "DeviceCategory": "游艺机",
        "ApprovalNumber": "34",
        "SupervisionPhone": "12318",
        "Link": "https://sh.gegia.cn/#/scanningView?id=his_2238"
      },
      {
        "Name": "快乐神箭手",
        "DeviceCategory": "游艺机",
        "ApprovalNumber": "680",
        "SupervisionPhone": "12318",
        "Link": "https://sh.gegia.cn/#/scanningView?id=his_1526"
      },
      {
        "Name": "疯狂弹弓",
        "DeviceCategory": "游艺机",
        "ApprovalNumber": "637",
        "SupervisionPhone": "12318",
        "Link": "https://sh.gegia.cn/#/scanningView?id=his_1798"
      },
      {
        "Name": "企鹅天地",
        "DeviceCategory": "游艺机",
        "ApprovalNumber": "631",
        "SupervisionPhone": "12318",
        "Link": "https://sh.gegia.cn/#/scanningView?id=his_1754"
      },
      {
        "Name": "魔法城堡",
        "DeviceCategory": "游艺机",
        "ApprovalNumber": "633",
        "SupervisionPhone": "12318",
        "Link": "https://sh.gegia.cn/#/scanningView?id=his_2398"
      },
      {
        "Name": "疯狂弹弓",
        "DeviceCategory": "游艺机",
        "ApprovalNumber": "637",
        "SupervisionPhone": "12318",
        "Link": "https://sh.gegia.cn/#/scanningView?id=his_2402"
      },
      {
        "Name": "糖果屋",
        "DeviceCategory": "游艺机",
        "ApprovalNumber": "29",
        "SupervisionPhone": "12318",
        "Link": "https://sh.gegia.cn/#/scanningView?id=his_2233"
      },
      {
        "Name": "神奇推手",
        "DeviceCategory": "游艺机",
        "ApprovalNumber": "33",
        "SupervisionPhone": "12318",
        "Link": "https://sh.gegia.cn/#/scanningView?id=his_2237"
      },
      {
        "Name": "疯狂射绳",
        "DeviceCategory": "游艺机",
        "ApprovalNumber": "679",
        "SupervisionPhone": "12318",
        "Link": "https://sh.gegia.cn/#/scanningView?id=his_1525"
      },
      {
        "Name": "超大娃娃机2",
        "DeviceCategory": "游艺机",
        "ApprovalNumber": "682",
        "SupervisionPhone": "12318",
        "Link": "https://sh.gegia.cn/#/scanningView?id=his_1529"
      },
      {
        "Name": "拳皇",
        "DeviceCategory": "游艺机",
        "ApprovalNumber": "632",
        "SupervisionPhone": "12318",
        "Link": "https://sh.gegia.cn/#/scanningView?id=his_2397"
      },
      {
        "Name": "PP虎2",
        "DeviceCategory": "游艺机",
        "ApprovalNumber": "636",
        "SupervisionPhone": "12318",
        "Link": "https://sh.gegia.cn/#/scanningView?id=his_2401"
      },
      {
        "Name": "梦幻射手Ⅲ（3）",
        "DeviceCategory": "游艺机",
        "ApprovalNumber": "28",
        "SupervisionPhone": "12318",
        "Link": "https://sh.gegia.cn/#/scanningView?id=his_2232"
      },
      {
        "Name": "方块达人",
        "DeviceCategory": "游艺机",
        "ApprovalNumber": "635",
        "SupervisionPhone": "12318",
        "Link": "https://sh.gegia.cn/#/scanningView?id=his_1788"
      },
      {
        "Name": "神奇双星",
        "DeviceCategory": "游艺机",
        "ApprovalNumber": "32",
        "SupervisionPhone": "12318",
        "Link": "https://sh.gegia.cn/#/scanningView?id=his_2236"
      },
      {
        "Name": "方块达人",
        "DeviceCategory": "游艺机",
        "ApprovalNumber": "635",
        "SupervisionPhone": "12318",
        "Link": "https://sh.gegia.cn/#/scanningView?id=his_2400"
      },
      {
        "Name": "神推手",
        "DeviceCategory": "游艺机",
        "ApprovalNumber": "545",
        "SupervisionPhone": "12318",
        "Link": "https://sh.gegia.cn/#/scanningView?id=his_2360"
      },
      {
        "Name": "开心吧",
        "DeviceCategory": "游艺机",
        "ApprovalNumber": "27",
        "SupervisionPhone": "12318",
        "Link": "https://sh.gegia.cn/#/scanningView?id=his_2231"
      },
      {
        "Name": "神奇剪刀-超大版",
        "DeviceCategory": "游艺机",
        "ApprovalNumber": "31",
        "SupervisionPhone": "12318",
        "Link": "https://sh.gegia.cn/#/scanningView?id=his_2235"
      },
      {
        "Name": "海洋嘉年华",
        "DeviceCategory": "游艺机",
        "ApprovalNumber": "681",
        "SupervisionPhone": "12318",
        "Link": "https://sh.gegia.cn/#/scanningView?id=his_1527"
      },
      {
        "Name": "PP虎2",
        "DeviceCategory": "游艺机",
        "ApprovalNumber": "636",
        "SupervisionPhone": "12318",
        "Link": "https://sh.gegia.cn/#/scanningView?id=his_1795"
      }
    ]
  }
]