[
  {
    "Type": "游艺设备",
    "Devices": [
      {
        "Name": "激流篮球",
        "DeviceCategory": "游艺机",
        "ApprovalNumber": "粤游审【2018】A126号",
        "SupervisionPhone": "12318",
        "Link": "https://sh.gegia.cn/user/login.do#/detail/product-catalog?formListType=%E5%B7%B2%E9%80%9A%E8%BF%87%E4%BA%A7%E5%93%81%E7%9B%AE%E5%BD%95&id=111&isChange=false&type=1"
      },
      {
        "Name": "黄金矿车（JP大奖）",
        "DeviceCategory": "游艺机",
        "ApprovalNumber": "粤游艺审〔2022〕22号",
        "SupervisionPhone": "12318",
        "Link": "https://sh.gegia.cn/user/login.do#/detail/product-catalog?formListType=%E5%B7%B2%E9%80%9A%E8%BF%87%E4%BA%A7%E5%93%81%E7%9B%AE%E5%BD%95&id=5192&isChange=false&type=1"
      },
      {
        "Name": "AR极地海洋馆",
        "DeviceCategory": "游艺机",
        "ApprovalNumber": "粤游艺审〔2021〕799号",
        "SupervisionPhone": "12318",
        "Link": "https://sh.gegia.cn/user/login.do#/detail/product-catalog?formListType=%E5%B7%B2%E9%80%9A%E8%BF%87%E4%BA%A7%E5%93%81%E7%9B%AE%E5%BD%95&id=4680&isChange=false&type=1"
      },
      {
        "Name": "AR幻想奇境",
        "DeviceCategory": "游艺机",
        "ApprovalNumber": "粤游艺审〔2021〕247号",
        "SupervisionPhone": "12318",
        "Link": "https://sh.gegia.cn/user/login.do#/detail/product-catalog?formListType=%E5%B7%B2%E9%80%9A%E8%BF%87%E4%BA%A7%E5%93%81%E7%9B%AE%E5%BD%95&id=4036&isChange=false&type=1"
      },
      {
        "Name": "奇趣蹦床",
        "DeviceCategory": "游艺机",
        "ApprovalNumber": "粤游艺审〔2021〕248号",
        "SupervisionPhone": "12318",
        "Link": "https://sh.gegia.cn/user/login.do#/detail/product-catalog?formListType=%E5%B7%B2%E9%80%9A%E8%BF%87%E4%BA%A7%E5%93%81%E7%9B%AE%E5%BD%95&id=4037&isChange=false&type=1"
      },
      {
        "Name": "你画我投",
        "DeviceCategory": "游艺机",
        "ApprovalNumber": "粤游艺审〔2021〕1号",
        "SupervisionPhone": "12318",
        "Link": "https://sh.gegia.cn/user/login.do#/detail/product-catalog?formListType=%E5%B7%B2%E9%80%9A%E8%BF%87%E4%BA%A7%E5%93%81%E7%9B%AE%E5%BD%95&id=3467&isChange=false&type=1"
      },
      {
        "Name": "奇趣滑梯",
        "DeviceCategory": "游艺机",
        "ApprovalNumber": "粤游审〔2020〕276号",
        "SupervisionPhone": "12318",
        "Link": "https://sh.gegia.cn/user/login.do#/detail/product-catalog?formListType=%E5%B7%B2%E9%80%9A%E8%BF%87%E4%BA%A7%E5%93%81%E7%9B%AE%E5%BD%95&id=3268&isChange=false&type=1"
      },
      {
        "Name": "小象赛跑（投影版）",
        "DeviceCategory": "游艺机",
        "ApprovalNumber": "粤游审〔2020〕279号",
        "SupervisionPhone": "12318",
        "Link": "https://sh.gegia.cn/user/login.do#/detail/product-catalog?formListType=%E5%B7%B2%E9%80%9A%E8%BF%87%E4%BA%A7%E5%93%81%E7%9B%AE%E5%BD%95&id=3275&isChange=false&type=1"
      },
      {
        "Name": "踢踏魔音",
        "DeviceCategory": "游艺机",
        "ApprovalNumber": "粤游审〔2020〕282号",
        "SupervisionPhone": "12318",
        "Link": "https://sh.gegia.cn/user/login.do#/detail/product-catalog?formListType=%E5%B7%B2%E9%80%9A%E8%BF%87%E4%BA%A7%E5%93%81%E7%9B%AE%E5%BD%95&id=3279&isChange=false&type=1"
      },
      {
        "Name": "小马快跑（投影版）",
        "DeviceCategory": "游艺机",
        "ApprovalNumber": "粤游审〔2020〕275号",
        "SupervisionPhone": "12318",
        "Link": "https://sh.gegia.cn/user/login.do#/detail/product-catalog?formListType=%E5%B7%B2%E9%80%9A%E8%BF%87%E4%BA%A7%E5%93%81%E7%9B%AE%E5%BD%95&id=3266&isChange=false&type=1"
      },
      {
        "Name": "蛋糕叠叠乐（投影版）",
        "DeviceCategory": "游艺机",
        "ApprovalNumber": "粤游审〔2020〕278号",
        "SupervisionPhone": "12318",
        "Link": "https://sh.gegia.cn/user/login.do#/detail/product-catalog?formListType=%E5%B7%B2%E9%80%9A%E8%BF%87%E4%BA%A7%E5%93%81%E7%9B%AE%E5%BD%95&id=3273&isChange=false&type=1"
      },
      {
        "Name": "冲刺甜甜圈",
        "DeviceCategory": "游艺机",
        "ApprovalNumber": "粤游审〔2020〕281号",
        "SupervisionPhone": "12318",
        "Link": "https://sh.gegia.cn/user/login.do#/detail/product-catalog?formListType=%E5%B7%B2%E9%80%9A%E8%BF%87%E4%BA%A7%E5%93%81%E7%9B%AE%E5%BD%95&id=3278&isChange=false&type=1"
      },
      {
        "Name": "卡路里酷跑（投影版）",
        "DeviceCategory": "游艺机",
        "ApprovalNumber": "粤游审〔2020〕277号",
        "SupervisionPhone": "12318",
        "Link": "https://sh.gegia.cn/user/login.do#/detail/product-catalog?formListType=%E5%B7%B2%E9%80%9A%E8%BF%87%E4%BA%A7%E5%93%81%E7%9B%AE%E5%BD%95&id=3270&isChange=false&type=1"
      },
      {
        "Name": "冲刺甜甜圈（投影版）",
        "DeviceCategory": "游艺机",
        "ApprovalNumber": "粤游审〔2020〕280号",
        "SupervisionPhone": "12318",
        "Link": "https://sh.gegia.cn/user/login.do#/detail/product-catalog?formListType=%E5%B7%B2%E9%80%9A%E8%BF%87%E4%BA%A7%E5%93%81%E7%9B%AE%E5%BD%95&id=3276&isChange=false&type=1"
      },
      {
        "Name": "蛋糕叠叠乐",
        "DeviceCategory": "游艺机",
        "ApprovalNumber": "粤游审〔2020〕1号",
        "SupervisionPhone": "12318",
        "Link": "https://sh.gegia.cn/user/login.do#/detail/product-catalog?formListType=%E5%B7%B2%E9%80%9A%E8%BF%87%E4%BA%A7%E5%93%81%E7%9B%AE%E5%BD%95&id=2636&isChange=false&type=1"
      },
      {
        "Name": "小马快跑",
        "DeviceCategory": "游艺机",
        "ApprovalNumber": "粤游审〔2020〕2号",
        "SupervisionPhone": "12318",
        "Link": "https://sh.gegia.cn/user/login.do#/detail/product-catalog?formListType=%E5%B7%B2%E9%80%9A%E8%BF%87%E4%BA%A7%E5%93%81%E7%9B%AE%E5%BD%95&id=2640&isChange=false&type=1"
      },
      {
        "Name": "奇幻旅程（加强版）",
        "DeviceCategory": "游艺机",
        "ApprovalNumber": "粤游审〔2019〕A309号",
        "SupervisionPhone": "12318",
        "Link": "https://sh.gegia.cn/user/login.do#/detail/product-catalog?formListType=%E5%B7%B2%E9%80%9A%E8%BF%87%E4%BA%A7%E5%93%81%E7%9B%AE%E5%BD%95&id=2203&isChange=false&type=1"
      },
      {
        "Name": "拯救小纵队",
        "DeviceCategory": "游艺机",
        "ApprovalNumber": "粤游审〔2019〕A310号",
        "SupervisionPhone": "12318",
        "Link": "https://sh.gegia.cn/user/login.do#/detail/product-catalog?formListType=%E5%B7%B2%E9%80%9A%E8%BF%87%E4%BA%A7%E5%93%81%E7%9B%AE%E5%BD%95&id=2215&isChange=false&type=1"
      },
      {
        "Name": "快来买鸭",
        "DeviceCategory": "游艺机",
        "ApprovalNumber": "粤游审〔2019〕A312号",
        "SupervisionPhone": "12318",
        "Link": "https://sh.gegia.cn/user/login.do#/detail/product-catalog?formListType=%E5%B7%B2%E9%80%9A%E8%BF%87%E4%BA%A7%E5%93%81%E7%9B%AE%E5%BD%95&id=2222&isChange=false&type=1"
      },
      {
        "Name": "超级飞侠卡片机",
        "DeviceCategory": "游艺机",
        "ApprovalNumber": "粤游审〔2019〕A311号",
        "SupervisionPhone": "12318",
        "Link": "https://sh.gegia.cn/user/login.do#/detail/product-catalog?formListType=%E5%B7%B2%E9%80%9A%E8%BF%87%E4%BA%A7%E5%93%81%E7%9B%AE%E5%BD%95&id=2221&isChange=false&type=1"
      },
      {
        "Name": "荧光舞动（豪华版）",
        "DeviceCategory": "游艺机",
        "ApprovalNumber": "粤游审〔2019〕A107号",
        "SupervisionPhone": "12318",
        "Link": "https://sh.gegia.cn/user/login.do#/detail/product-catalog?formListType=%E5%B7%B2%E9%80%9A%E8%BF%87%E4%BA%A7%E5%93%81%E7%9B%AE%E5%BD%95&id=1919&isChange=false&type=1"
      },
      {
        "Name": "神秘大咖",
        "DeviceCategory": "游艺机",
        "ApprovalNumber": "粤游审〔2019〕A106号",
        "SupervisionPhone": "12318",
        "Link": "https://sh.gegia.cn/user/login.do#/detail/product-catalog?formListType=%E5%B7%B2%E9%80%9A%E8%BF%87%E4%BA%A7%E5%93%81%E7%9B%AE%E5%BD%95&id=1907&isChange=false&type=1"
      },
      {
        "Name": "敲击棒棒团加强版",
        "DeviceCategory": "游艺机",
        "ApprovalNumber": "粤游审〔2019〕A105号",
        "SupervisionPhone": "12318",
        "Link": "https://sh.gegia.cn/user/login.do#/detail/product-catalog?formListType=%E5%B7%B2%E9%80%9A%E8%BF%87%E4%BA%A7%E5%93%81%E7%9B%AE%E5%BD%95&id=1802&isChange=false&type=1"
      },
      {
        "Name": "奇幻旅程",
        "DeviceCategory": "游艺机",
        "ApprovalNumber": "粤游审【2019】A001号",
        "SupervisionPhone": "12318",
        "Link": "https://sh.gegia.cn/user/login.do#/detail/product-catalog?formListType=%E5%B7%B2%E9%80%9A%E8%BF%87%E4%BA%A7%E5%93%81%E7%9B%AE%E5%BD%95&id=1573&isChange=false&type=1"
      },
      {
        "Name": "荧光舞动",
        "DeviceCategory": "游艺机",
        "ApprovalNumber": "粤游审【2019】A002号",
        "SupervisionPhone": "12318",
        "Link": "https://sh.gegia.cn/user/login.do#/detail/product-catalog?formListType=%E5%B7%B2%E9%80%9A%E8%BF%87%E4%BA%A7%E5%93%81%E7%9B%AE%E5%BD%95&id=1605&isChange=false&type=1"
      },
      {
        "Name": "糖果泡泡触屏版",
        "DeviceCategory": "游艺机",
        "ApprovalNumber": "粤游审〔2018〕A472号",
        "SupervisionPhone": "12318",
        "Link": "https://sh.gegia.cn/user/login.do#/detail/product-catalog?formListType=%E5%B7%B2%E9%80%9A%E8%BF%87%E4%BA%A7%E5%93%81%E7%9B%AE%E5%BD%95&id=784&isChange=false&type=1"
      },
      {
        "Name": "恋之物语",
        "DeviceCategory": "游艺机",
        "ApprovalNumber": "粤游审〔2018〕A471号",
        "SupervisionPhone": "12318",
        "Link": "https://sh.gegia.cn/user/login.do#/detail/product-catalog?formListType=%E5%B7%B2%E9%80%9A%E8%BF%87%E4%BA%A7%E5%93%81%E7%9B%AE%E5%BD%95&id=783&isChange=false&type=1"
      },
      {
        "Name": "跳跳乐",
        "DeviceCategory": "游艺机",
        "ApprovalNumber": "粤游审〔2018〕A473号",
        "SupervisionPhone": "12318",
        "Link": "https://sh.gegia.cn/user/login.do#/detail/product-catalog?formListType=%E5%B7%B2%E9%80%9A%E8%BF%87%E4%BA%A7%E5%93%81%E7%9B%AE%E5%BD%95&id=933&isChange=false&type=1"
      },
      {
        "Name": "超级大明猩",
        "DeviceCategory": "游艺机",
        "ApprovalNumber": "粤游审【2018】A123号",
        "SupervisionPhone": "12318",
        "Link": "https://sh.gegia.cn/user/login.do#/detail/product-catalog?formListType=%E5%B7%B2%E9%80%9A%E8%BF%87%E4%BA%A7%E5%93%81%E7%9B%AE%E5%BD%95&id=129&isChange=false&type=1"
      },
      {
        "Name": "糖果泡泡",
        "DeviceCategory": "游艺机",
        "ApprovalNumber": "粤游审【2018】A125号",
        "SupervisionPhone": "12318",
        "Link": "https://sh.gegia.cn/user/login.do#/detail/product-catalog?formListType=%E5%B7%B2%E9%80%9A%E8%BF%87%E4%BA%A7%E5%93%81%E7%9B%AE%E5%BD%95&id=120&isChange=false&type=1"
      },
      {
        "Name": "恐龙世纪-大水炮",
        "DeviceCategory": "游艺机",
        "ApprovalNumber": "粤游审【2018】A124号",
        "SupervisionPhone": "12318",
        "Link": "https://sh.gegia.cn/user/login.do#/detail/product-catalog?formListType=%E5%B7%B2%E9%80%9A%E8%BF%87%E4%BA%A7%E5%93%81%E7%9B%AE%E5%BD%95&id=118&isChange=false&type=1"
      },
      {
        "Name": "恐龙世纪-大水炮",
        "DeviceCategory": "游艺机",
        "ApprovalNumber": "粤游审〔2018〕A124号",
        "SupervisionPhone": "12318",
        "Link": "https://sh.gegia.cn/user/login.do#/detail/product-catalog?formListType=%E5%B7%B2%E9%80%9A%E8%BF%87%E4%BA%A7%E5%93%81%E7%9B%AE%E5%BD%95&id=his_1473&isChange=false&type=1"
      },
      {
        "Name": "超级大明猩",
        "DeviceCategory": "游艺机",
        "ApprovalNumber": "粤游审〔2018〕A123号",
        "SupervisionPhone": "12318",
        "Link": "https://sh.gegia.cn/user/login.do#/detail/product-catalog?formListType=%E5%B7%B2%E9%80%9A%E8%BF%87%E4%BA%A7%E5%93%81%E7%9B%AE%E5%BD%95&id=his_1472&isChange=false&type=1"
      },
      {
        "Name": "激流篮球",
        "DeviceCategory": "游艺机",
        "ApprovalNumber": "粤游审〔2018〕A126号",
        "SupervisionPhone": "12318",
        "Link": "https://sh.gegia.cn/user/login.do#/detail/product-catalog?formListType=%E5%B7%B2%E9%80%9A%E8%BF%87%E4%BA%A7%E5%93%81%E7%9B%AE%E5%BD%95&id=his_1475&isChange=false&type=1"
      },
      {
        "Name": "糖果泡泡",
        "DeviceCategory": "游艺机",
        "ApprovalNumber": "粤游审〔2018〕A125号",
        "SupervisionPhone": "12318",
        "Link": "https://sh.gegia.cn/user/login.do#/detail/product-catalog?formListType=%E5%B7%B2%E9%80%9A%E8%BF%87%E4%BA%A7%E5%93%81%E7%9B%AE%E5%BD%95&id=his_1474&isChange=false&type=1"
      },
      {
        "Name": "节奏冲击",
        "DeviceCategory": "游艺机",
        "ApprovalNumber": "粤游审〔2017〕A768号",
        "SupervisionPhone": "12318",
        "Link": "https://sh.gegia.cn/user/login.do#/detail/product-catalog?formListType=%E5%B7%B2%E9%80%9A%E8%BF%87%E4%BA%A7%E5%93%81%E7%9B%AE%E5%BD%95&id=his_864&isChange=false&type=1"
      },
      {
        "Name": "奇趣波波池",
        "DeviceCategory": "游艺机",
        "ApprovalNumber": "粤游审〔2017〕A023号",
        "SupervisionPhone": "12318",
        "Link": "https://sh.gegia.cn/user/login.do#/detail/product-catalog?formListType=%E5%B7%B2%E9%80%9A%E8%BF%87%E4%BA%A7%E5%93%81%E7%9B%AE%E5%BD%95&id=his_28&isChange=false&type=1"
      },
      {
        "Name": "《神笔酷甩》小画板",
        "DeviceCategory": "游艺机",
        "ApprovalNumber": "粤游审〔2017〕A221号",
        "SupervisionPhone": "12318",
        "Link": "https://sh.gegia.cn/user/login.do#/detail/product-catalog?formListType=%E5%B7%B2%E9%80%9A%E8%BF%87%E4%BA%A7%E5%93%81%E7%9B%AE%E5%BD%95&id=his_302&isChange=false&type=1"
      },
      {
        "Name": "一剪同萌",
        "DeviceCategory": "游艺机",
        "ApprovalNumber": "粤游审〔2017〕A767号",
        "SupervisionPhone": "12318",
        "Link": "https://sh.gegia.cn/user/login.do#/detail/product-catalog?formListType=%E5%B7%B2%E9%80%9A%E8%BF%87%E4%BA%A7%E5%93%81%E7%9B%AE%E5%BD%95&id=his_863&isChange=false&type=1"
      },
      {
        "Name": "顽皮大明猩DX",
        "DeviceCategory": "游艺机",
        "ApprovalNumber": "粤游审〔2017〕A026号",
        "SupervisionPhone": "12318",
        "Link": "https://sh.gegia.cn/user/login.do#/detail/product-catalog?formListType=%E5%B7%B2%E9%80%9A%E8%BF%87%E4%BA%A7%E5%93%81%E7%9B%AE%E5%BD%95&id=his_31&isChange=false&type=1"
      },
      {
        "Name": "《欢乐小企鹅（加强版）》",
        "DeviceCategory": "游艺机",
        "ApprovalNumber": "粤游审〔2017〕A220号",
        "SupervisionPhone": "12318",
        "Link": "https://sh.gegia.cn/user/login.do#/detail/product-catalog?formListType=%E5%B7%B2%E9%80%9A%E8%BF%87%E4%BA%A7%E5%93%81%E7%9B%AE%E5%BD%95&id=his_301&isChange=false&type=1"
      },
      {
        "Name": "奇趣钓鱼池",
        "DeviceCategory": "游艺机",
        "ApprovalNumber": "粤游审〔2017〕A766号",
        "SupervisionPhone": "12318",
        "Link": "https://sh.gegia.cn/user/login.do#/detail/product-catalog?formListType=%E5%B7%B2%E9%80%9A%E8%BF%87%E4%BA%A7%E5%93%81%E7%9B%AE%E5%BD%95&id=his_862&isChange=false&type=1"
      },
      {
        "Name": "酷卡家族-雪球大战",
        "DeviceCategory": "游艺机",
        "ApprovalNumber": "粤游审〔2017〕A024号",
        "SupervisionPhone": "12318",
        "Link": "https://sh.gegia.cn/user/login.do#/detail/product-catalog?formListType=%E5%B7%B2%E9%80%9A%E8%BF%87%E4%BA%A7%E5%93%81%E7%9B%AE%E5%BD%95&id=his_30&isChange=false&type=1"
      },
      {
        "Name": "《星乐幻想》",
        "DeviceCategory": "游艺机",
        "ApprovalNumber": "粤游审〔2017〕A458号",
        "SupervisionPhone": "12318",
        "Link": "https://sh.gegia.cn/user/login.do#/detail/product-catalog?formListType=%E5%B7%B2%E9%80%9A%E8%BF%87%E4%BA%A7%E5%93%81%E7%9B%AE%E5%BD%95&id=his_550&isChange=false&type=1"
      },
      {
        "Name": "奇趣沙城·无限山河",
        "DeviceCategory": "游艺机",
        "ApprovalNumber": "粤游审〔2016〕A097号",
        "SupervisionPhone": "12318",
        "Link": "https://sh.gegia.cn/user/login.do#/detail/product-catalog?formListType=%E5%B7%B2%E9%80%9A%E8%BF%87%E4%BA%A7%E5%93%81%E7%9B%AE%E5%BD%95&id=his_1116&isChange=false&type=1"
      },
      {
        "Name": "百变笨鸡  V1.0",
        "DeviceCategory": "游艺机",
        "ApprovalNumber": "粤游审〔2016〕A238号",
        "SupervisionPhone": "12318",
        "Link": "https://sh.gegia.cn/user/login.do#/detail/product-catalog?formListType=%E5%B7%B2%E9%80%9A%E8%BF%87%E4%BA%A7%E5%93%81%E7%9B%AE%E5%BD%95&id=his_1256&isChange=false&type=1"
      },
      {
        "Name": "钓鱼小达人",
        "DeviceCategory": "游艺机",
        "ApprovalNumber": "粤游审〔2016〕A032号",
        "SupervisionPhone": "12318",
        "Link": "https://sh.gegia.cn/user/login.do#/detail/product-catalog?formListType=%E5%B7%B2%E9%80%9A%E8%BF%87%E4%BA%A7%E5%93%81%E7%9B%AE%E5%BD%95&id=his_202&isChange=false&type=1"
      },
      {
        "Name": "奇趣沙城",
        "DeviceCategory": "游艺机",
        "ApprovalNumber": "粤游审〔2016〕A034号",
        "SupervisionPhone": "12318",
        "Link": "https://sh.gegia.cn/user/login.do#/detail/product-catalog?formListType=%E5%B7%B2%E9%80%9A%E8%BF%87%E4%BA%A7%E5%93%81%E7%9B%AE%E5%BD%95&id=his_222&isChange=false&type=1"
      },
      {
        "Name": "欢乐宝贝",
        "DeviceCategory": "游艺机",
        "ApprovalNumber": "粤游审〔2016〕A098号",
        "SupervisionPhone": "12318",
        "Link": "https://sh.gegia.cn/user/login.do#/detail/product-catalog?formListType=%E5%B7%B2%E9%80%9A%E8%BF%87%E4%BA%A7%E5%93%81%E7%9B%AE%E5%BD%95&id=his_1117&isChange=false&type=1"
      },
      {
        "Name": "单车酷跑2  V1.0",
        "DeviceCategory": "游艺机",
        "ApprovalNumber": "粤游审〔2016〕A239号",
        "SupervisionPhone": "12318",
        "Link": "https://sh.gegia.cn/user/login.do#/detail/product-catalog?formListType=%E5%B7%B2%E9%80%9A%E8%BF%87%E4%BA%A7%E5%93%81%E7%9B%AE%E5%BD%95&id=his_1257&isChange=false&type=1"
      },
      {
        "Name": "逃离动物园卡片版",
        "DeviceCategory": "游艺机",
        "ApprovalNumber": "粤游审〔2016〕A033号",
        "SupervisionPhone": "12318",
        "Link": "https://sh.gegia.cn/user/login.do#/detail/product-catalog?formListType=%E5%B7%B2%E9%80%9A%E8%BF%87%E4%BA%A7%E5%93%81%E7%9B%AE%E5%BD%95&id=his_221&isChange=false&type=1"
      },
      {
        "Name": "疯狂的小鸟",
        "DeviceCategory": "游艺机",
        "ApprovalNumber": "粤游审〔2016〕A031号",
        "SupervisionPhone": "12318",
        "Link": "https://sh.gegia.cn/user/login.do#/detail/product-catalog?formListType=%E5%B7%B2%E9%80%9A%E8%BF%87%E4%BA%A7%E5%93%81%E7%9B%AE%E5%BD%95&id=his_200&isChange=false&type=1"
      },
      {
        "Name": "宝贝大冒险",
        "DeviceCategory": "游艺机",
        "ApprovalNumber": "粤游审〔2016〕A096号",
        "SupervisionPhone": "12318",
        "Link": "https://sh.gegia.cn/user/login.do#/detail/product-catalog?formListType=%E5%B7%B2%E9%80%9A%E8%BF%87%E4%BA%A7%E5%93%81%E7%9B%AE%E5%BD%95&id=his_1115&isChange=false&type=1"
      },
      {
        "Name": "节奏小车手  V1.0",
        "DeviceCategory": "游艺机",
        "ApprovalNumber": "粤游审〔2016〕A237号",
        "SupervisionPhone": "12318",
        "Link": "https://sh.gegia.cn/user/login.do#/detail/product-catalog?formListType=%E5%B7%B2%E9%80%9A%E8%BF%87%E4%BA%A7%E5%93%81%E7%9B%AE%E5%BD%95&id=his_1255&isChange=false&type=1"
      },
      {
        "Name": "欢乐小象  V1.0",
        "DeviceCategory": "游艺机",
        "ApprovalNumber": "粤游审〔2016〕A241号",
        "SupervisionPhone": "12318",
        "Link": "https://sh.gegia.cn/user/login.do#/detail/product-catalog?formListType=%E5%B7%B2%E9%80%9A%E8%BF%87%E4%BA%A7%E5%93%81%E7%9B%AE%E5%BD%95&id=his_1259&isChange=false&type=1"
      },
      {
        "Name": "电激魔方",
        "DeviceCategory": "游艺机",
        "ApprovalNumber": "粤游审〔2015〕A113号",
        "SupervisionPhone": "12318",
        "Link": "https://sh.gegia.cn/user/login.do#/detail/product-catalog?formListType=%E5%B7%B2%E9%80%9A%E8%BF%87%E4%BA%A7%E5%93%81%E7%9B%AE%E5%BD%95&id=his_1613&isChange=false&type=1"
      },
      {
        "Name": "单车酷跑",
        "DeviceCategory": "游艺机",
        "ApprovalNumber": "粤游审〔2015〕A112号",
        "SupervisionPhone": "12318",
        "Link": "https://sh.gegia.cn/user/login.do#/detail/product-catalog?formListType=%E5%B7%B2%E9%80%9A%E8%BF%87%E4%BA%A7%E5%93%81%E7%9B%AE%E5%BD%95&id=his_1612&isChange=false&type=1"
      },
      {
        "Name": "顽皮运动会",
        "DeviceCategory": "游艺机",
        "ApprovalNumber": "粤游审〔2015〕A192号",
        "SupervisionPhone": "12318",
        "Link": "https://sh.gegia.cn/user/login.do#/detail/product-catalog?formListType=%E5%B7%B2%E9%80%9A%E8%BF%87%E4%BA%A7%E5%93%81%E7%9B%AE%E5%BD%95&id=his_1655&isChange=false&type=1"
      },
      {
        "Name": "恐龙世纪水枪版",
        "DeviceCategory": "游艺机",
        "ApprovalNumber": "粤游审〔2015〕A111号",
        "SupervisionPhone": "12318",
        "Link": "https://sh.gegia.cn/user/login.do#/detail/product-catalog?formListType=%E5%B7%B2%E9%80%9A%E8%BF%87%E4%BA%A7%E5%93%81%E7%9B%AE%E5%BD%95&id=his_1611&isChange=false&type=1"
      },
      {
        "Name": "盒子世界 ",
        "DeviceCategory": "游艺机",
        "ApprovalNumber": "文游备粤字【2013】5号",
        "SupervisionPhone": "12318",
        "Link": "https://sh.gegia.cn/user/login.do#/detail/product-catalog?formListType=%E5%B7%B2%E9%80%9A%E8%BF%87%E4%BA%A7%E5%93%81%E7%9B%AE%E5%BD%95&id=his_2517&isChange=false&type=1"
      },
      {
        "Name": "疯狂企鹅乐园",
        "DeviceCategory": "游艺机",
        "ApprovalNumber": "文游备粤字【2013】2号",
        "SupervisionPhone": "12318",
        "Link": "https://sh.gegia.cn/user/login.do#/detail/product-catalog?formListType=%E5%B7%B2%E9%80%9A%E8%BF%87%E4%BA%A7%E5%93%81%E7%9B%AE%E5%BD%95&id=his_2323&isChange=false&type=1"
      },
      {
        "Name": "哇哇总动员 ",
        "DeviceCategory": "游艺机",
        "ApprovalNumber": "文游备粤字【2013】8号",
        "SupervisionPhone": "12318",
        "Link": "https://sh.gegia.cn/user/login.do#/detail/product-catalog?formListType=%E5%B7%B2%E9%80%9A%E8%BF%87%E4%BA%A7%E5%93%81%E7%9B%AE%E5%BD%95&id=his_2520&isChange=false&type=1"
      },
      {
        "Name": "三国演武（单人版）",
        "DeviceCategory": "游艺机",
        "ApprovalNumber": "文游备粤字【2013】4号",
        "SupervisionPhone": "12318",
        "Link": "https://sh.gegia.cn/user/login.do#/detail/product-catalog?formListType=%E5%B7%B2%E9%80%9A%E8%BF%87%E4%BA%A7%E5%93%81%E7%9B%AE%E5%BD%95&id=his_2516&isChange=false&type=1"
      },
      {
        "Name": "疯狂大灌篮 ",
        "DeviceCategory": "游艺机",
        "ApprovalNumber": "文游备粤字【2013】7号",
        "SupervisionPhone": "12318",
        "Link": "https://sh.gegia.cn/user/login.do#/detail/product-catalog?formListType=%E5%B7%B2%E9%80%9A%E8%BF%87%E4%BA%A7%E5%93%81%E7%9B%AE%E5%BD%95&id=his_2519&isChange=false&type=1"
      },
      {
        "Name": "玩偶魔方2 ",
        "DeviceCategory": "游艺机",
        "ApprovalNumber": "文游备粤字【2013】6号",
        "SupervisionPhone": "12318",
        "Link": "https://sh.gegia.cn/user/login.do#/detail/product-catalog?formListType=%E5%B7%B2%E9%80%9A%E8%BF%87%E4%BA%A7%E5%93%81%E7%9B%AE%E5%BD%95&id=his_2518&isChange=false&type=1"
      },
      {
        "Name": "三国演武（双人版）",
        "DeviceCategory": "游艺机",
        "ApprovalNumber": "文游备粤字【2013】3号",
        "SupervisionPhone": "12318",
        "Link": "https://sh.gegia.cn/user/login.do#/detail/product-catalog?formListType=%E5%B7%B2%E9%80%9A%E8%BF%87%E4%BA%A7%E5%93%81%E7%9B%AE%E5%BD%95&id=his_2324&isChange=false&type=1"
      },
      {
        "Name": "玩偶魔方",
        "DeviceCategory": "游艺机",
        "ApprovalNumber": "文游备粤字【2012】42号",
        "SupervisionPhone": "12318",
        "Link": "https://sh.gegia.cn/user/login.do#/detail/product-catalog?formListType=%E5%B7%B2%E9%80%9A%E8%BF%87%E4%BA%A7%E5%93%81%E7%9B%AE%E5%BD%95&id=his_2150&isChange=false&type=1"
      },
      {
        "Name": "彩蛋农场",
        "DeviceCategory": "游艺机",
        "ApprovalNumber": "文游备粤字【2012】41号",
        "SupervisionPhone": "12318",
        "Link": "https://sh.gegia.cn/user/login.do#/detail/product-catalog?formListType=%E5%B7%B2%E9%80%9A%E8%BF%87%E4%BA%A7%E5%93%81%E7%9B%AE%E5%BD%95&id=his_2149&isChange=false&type=1"
      },
      {
        "Name": "非诚勿扰",
        "DeviceCategory": "游艺机",
        "ApprovalNumber": "文游备粤字【2012】44号",
        "SupervisionPhone": "12318",
        "Link": "https://sh.gegia.cn/user/login.do#/detail/product-catalog?formListType=%E5%B7%B2%E9%80%9A%E8%BF%87%E4%BA%A7%E5%93%81%E7%9B%AE%E5%BD%95&id=his_2152&isChange=false&type=1"
      },
      {
        "Name": "炫次方（单、双机）豪华版",
        "DeviceCategory": "游艺机",
        "ApprovalNumber": "文游备粤字【2012】110号",
        "SupervisionPhone": "12318",
        "Link": "https://sh.gegia.cn/user/login.do#/detail/product-catalog?formListType=%E5%B7%B2%E9%80%9A%E8%BF%87%E4%BA%A7%E5%93%81%E7%9B%AE%E5%BD%95&id=his_2175&isChange=false&type=1"
      },
      {
        "Name": "希力指多星2",
        "DeviceCategory": "游艺机",
        "ApprovalNumber": "文游备粤字【2012】43号",
        "SupervisionPhone": "12318",
        "Link": "https://sh.gegia.cn/user/login.do#/detail/product-catalog?formListType=%E5%B7%B2%E9%80%9A%E8%BF%87%E4%BA%A7%E5%93%81%E7%9B%AE%E5%BD%95&id=his_2151&isChange=false&type=1"
      },
      {
        "Name": "敲击棒棒团",
        "DeviceCategory": "游艺机",
        "ApprovalNumber": "文游备粤字【2011】19号",
        "SupervisionPhone": "12318",
        "Link": "https://sh.gegia.cn/user/login.do#/detail/product-catalog?formListType=%E5%B7%B2%E9%80%9A%E8%BF%87%E4%BA%A7%E5%93%81%E7%9B%AE%E5%BD%95&id=his_2105&isChange=false&type=1"
      },
      {
        "Name": "海洋之星Ⅱ代4人平装版",
        "DeviceCategory": "游艺机",
        "ApprovalNumber": "文游备粤字【2010】3号",
        "SupervisionPhone": "12318",
        "Link": "https://sh.gegia.cn/user/login.do#/detail/product-catalog?formListType=%E5%B7%B2%E9%80%9A%E8%BF%87%E4%BA%A7%E5%93%81%E7%9B%AE%E5%BD%95&id=his_2050&isChange=false&type=1"
      },
      {
        "Name": "希力猫抓老鼠",
        "DeviceCategory": "游艺机",
        "ApprovalNumber": "文游备粤字【2010】7号",
        "SupervisionPhone": "12318",
        "Link": "https://sh.gegia.cn/user/login.do#/detail/product-catalog?formListType=%E5%B7%B2%E9%80%9A%E8%BF%87%E4%BA%A7%E5%93%81%E7%9B%AE%E5%BD%95&id=his_2054&isChange=false&type=1"
      },
      {
        "Name": "疯狂企鹅乐园",
        "DeviceCategory": "游艺机",
        "ApprovalNumber": "文游备粤字【2010】11号",
        "SupervisionPhone": "12318",
        "Link": "https://sh.gegia.cn/user/login.do#/detail/product-catalog?formListType=%E5%B7%B2%E9%80%9A%E8%BF%87%E4%BA%A7%E5%93%81%E7%9B%AE%E5%BD%95&id=his_2058&isChange=false&type=1"
      },
      {
        "Name": "希力大喝雄兵",
        "DeviceCategory": "游艺机",
        "ApprovalNumber": "文游备粤字【2010】15号",
        "SupervisionPhone": "12318",
        "Link": "https://sh.gegia.cn/user/login.do#/detail/product-catalog?formListType=%E5%B7%B2%E9%80%9A%E8%BF%87%E4%BA%A7%E5%93%81%E7%9B%AE%E5%BD%95&id=his_2062&isChange=false&type=1"
      },
      {
        "Name": "希力丛林运动会",
        "DeviceCategory": "游艺机",
        "ApprovalNumber": "文游备粤字【2010】2号",
        "SupervisionPhone": "12318",
        "Link": "https://sh.gegia.cn/user/login.do#/detail/product-catalog?formListType=%E5%B7%B2%E9%80%9A%E8%BF%87%E4%BA%A7%E5%93%81%E7%9B%AE%E5%BD%95&id=his_2049&isChange=false&type=1"
      },
      {
        "Name": "希力吃火锅",
        "DeviceCategory": "游艺机",
        "ApprovalNumber": "文游备粤字【2010】6号",
        "SupervisionPhone": "12318",
        "Link": "https://sh.gegia.cn/user/login.do#/detail/product-catalog?formListType=%E5%B7%B2%E9%80%9A%E8%BF%87%E4%BA%A7%E5%93%81%E7%9B%AE%E5%BD%95&id=his_2053&isChange=false&type=1"
      },
      {
        "Name": "希力疯狂摩托",
        "DeviceCategory": "游艺机",
        "ApprovalNumber": "文游备粤字【2010】10号",
        "SupervisionPhone": "12318",
        "Link": "https://sh.gegia.cn/user/login.do#/detail/product-catalog?formListType=%E5%B7%B2%E9%80%9A%E8%BF%87%E4%BA%A7%E5%93%81%E7%9B%AE%E5%BD%95&id=his_2057&isChange=false&type=1"
      },
      {
        "Name": "希力丛林大营救",
        "DeviceCategory": "游艺机",
        "ApprovalNumber": "文游备粤字【2010】14号",
        "SupervisionPhone": "12318",
        "Link": "https://sh.gegia.cn/user/login.do#/detail/product-catalog?formListType=%E5%B7%B2%E9%80%9A%E8%BF%87%E4%BA%A7%E5%93%81%E7%9B%AE%E5%BD%95&id=his_2061&isChange=false&type=1"
      },
      {
        "Name": "锵锵斗地主二代",
        "DeviceCategory": "游艺机",
        "ApprovalNumber": "文游备粤字【2010】18号",
        "SupervisionPhone": "12318",
        "Link": "https://sh.gegia.cn/user/login.do#/detail/product-catalog?formListType=%E5%B7%B2%E9%80%9A%E8%BF%87%E4%BA%A7%E5%93%81%E7%9B%AE%E5%BD%95&id=his_2065&isChange=false&type=1"
      },
      {
        "Name": "希力倾城之恋",
        "DeviceCategory": "游艺机",
        "ApprovalNumber": "文游备粤字【2010】1号",
        "SupervisionPhone": "12318",
        "Link": "https://sh.gegia.cn/user/login.do#/detail/product-catalog?formListType=%E5%B7%B2%E9%80%9A%E8%BF%87%E4%BA%A7%E5%93%81%E7%9B%AE%E5%BD%95&id=his_2048&isChange=false&type=1"
      },
      {
        "Name": "海洋之星Ⅱ代4人精装版",
        "DeviceCategory": "游艺机",
        "ApprovalNumber": "文游备粤字【2010】5号",
        "SupervisionPhone": "12318",
        "Link": "https://sh.gegia.cn/user/login.do#/detail/product-catalog?formListType=%E5%B7%B2%E9%80%9A%E8%BF%87%E4%BA%A7%E5%93%81%E7%9B%AE%E5%BD%95&id=his_2052&isChange=false&type=1"
      },
      {
        "Name": "希力越狱",
        "DeviceCategory": "游艺机",
        "ApprovalNumber": "文游备粤字【2010】9号",
        "SupervisionPhone": "12318",
        "Link": "https://sh.gegia.cn/user/login.do#/detail/product-catalog?formListType=%E5%B7%B2%E9%80%9A%E8%BF%87%E4%BA%A7%E5%93%81%E7%9B%AE%E5%BD%95&id=his_2056&isChange=false&type=1"
      },
      {
        "Name": "希力捣蛋赛跑",
        "DeviceCategory": "游艺机",
        "ApprovalNumber": "文游备粤字【2010】13号",
        "SupervisionPhone": "12318",
        "Link": "https://sh.gegia.cn/user/login.do#/detail/product-catalog?formListType=%E5%B7%B2%E9%80%9A%E8%BF%87%E4%BA%A7%E5%93%81%E7%9B%AE%E5%BD%95&id=his_2060&isChange=false&type=1"
      },
      {
        "Name": "希力足球小将",
        "DeviceCategory": "游艺机",
        "ApprovalNumber": "文游备粤字【2010】17号",
        "SupervisionPhone": "12318",
        "Link": "https://sh.gegia.cn/user/login.do#/detail/product-catalog?formListType=%E5%B7%B2%E9%80%9A%E8%BF%87%E4%BA%A7%E5%93%81%E7%9B%AE%E5%BD%95&id=his_2064&isChange=false&type=1"
      },
      {
        "Name": "海洋之星Ⅱ代6人豪华版",
        "DeviceCategory": "游艺机",
        "ApprovalNumber": "文游备粤字【2010】4号",
        "SupervisionPhone": "12318",
        "Link": "https://sh.gegia.cn/user/login.do#/detail/product-catalog?formListType=%E5%B7%B2%E9%80%9A%E8%BF%87%E4%BA%A7%E5%93%81%E7%9B%AE%E5%BD%95&id=his_2051&isChange=false&type=1"
      },
      {
        "Name": "海洋之星Ⅱ代6人精装版",
        "DeviceCategory": "游艺机",
        "ApprovalNumber": "文游备粤字【2010】8号",
        "SupervisionPhone": "12318",
        "Link": "https://sh.gegia.cn/user/login.do#/detail/product-catalog?formListType=%E5%B7%B2%E9%80%9A%E8%BF%87%E4%BA%A7%E5%93%81%E7%9B%AE%E5%BD%95&id=his_2055&isChange=false&type=1"
      },
      {
        "Name": "希力海洋之星",
        "DeviceCategory": "游艺机",
        "ApprovalNumber": "文游备粤字【2010】12号",
        "SupervisionPhone": "12318",
        "Link": "https://sh.gegia.cn/user/login.do#/detail/product-catalog?formListType=%E5%B7%B2%E9%80%9A%E8%BF%87%E4%BA%A7%E5%93%81%E7%9B%AE%E5%BD%95&id=his_2059&isChange=false&type=1"
      },
      {
        "Name": "希力挑战科比",
        "DeviceCategory": "游艺机",
        "ApprovalNumber": "文游备粤字【2010】16号",
        "SupervisionPhone": "12318",
        "Link": "https://sh.gegia.cn/user/login.do#/detail/product-catalog?formListType=%E5%B7%B2%E9%80%9A%E8%BF%87%E4%BA%A7%E5%93%81%E7%9B%AE%E5%BD%95&id=his_2063&isChange=false&type=1"
      },
      {
        "Name": "指多星",
        "DeviceCategory": "游艺机",
        "ApprovalNumber": "GS-2009-1-156",
        "SupervisionPhone": "12318",
        "Link": "https://sh.gegia.cn/user/login.do#/detail/product-catalog?formListType=%E5%B7%B2%E9%80%9A%E8%BF%87%E4%BA%A7%E5%93%81%E7%9B%AE%E5%BD%95&id=his_1870&isChange=false&type=1"
      },
      {
        "Name": "打妖怪",
        "DeviceCategory": "游艺机",
        "ApprovalNumber": "GS-2009-1-160",
        "SupervisionPhone": "12318",
        "Link": "https://sh.gegia.cn/user/login.do#/detail/product-catalog?formListType=%E5%B7%B2%E9%80%9A%E8%BF%87%E4%BA%A7%E5%93%81%E7%9B%AE%E5%BD%95&id=his_1874&isChange=false&type=1"
      },
      {
        "Name": "抓青蛙",
        "DeviceCategory": "游艺机",
        "ApprovalNumber": "GS-2009-1-159",
        "SupervisionPhone": "12318",
        "Link": "https://sh.gegia.cn/user/login.do#/detail/product-catalog?formListType=%E5%B7%B2%E9%80%9A%E8%BF%87%E4%BA%A7%E5%93%81%E7%9B%AE%E5%BD%95&id=his_1873&isChange=false&type=1"
      },
      {
        "Name": "忍者镖",
        "DeviceCategory": "游艺机",
        "ApprovalNumber": "GS-2009-1-158",
        "SupervisionPhone": "12318",
        "Link": "https://sh.gegia.cn/user/login.do#/detail/product-catalog?formListType=%E5%B7%B2%E9%80%9A%E8%BF%87%E4%BA%A7%E5%93%81%E7%9B%AE%E5%BD%95&id=his_1872&isChange=false&type=1"
      },
      {
        "Name": "打蚊子",
        "DeviceCategory": "游艺机",
        "ApprovalNumber": "GS-2009-1-162",
        "SupervisionPhone": "12318",
        "Link": "https://sh.gegia.cn/user/login.do#/detail/product-catalog?formListType=%E5%B7%B2%E9%80%9A%E8%BF%87%E4%BA%A7%E5%93%81%E7%9B%AE%E5%BD%95&id=his_1876&isChange=false&type=1"
      },
      {
        "Name": "开心飞球",
        "DeviceCategory": "游艺机",
        "ApprovalNumber": "GS-2009-1-157",
        "SupervisionPhone": "12318",
        "Link": "https://sh.gegia.cn/user/login.do#/detail/product-catalog?formListType=%E5%B7%B2%E9%80%9A%E8%BF%87%E4%BA%A7%E5%93%81%E7%9B%AE%E5%BD%95&id=his_1871&isChange=false&type=1"
      },
      {
        "Name": "打坏狗",
        "DeviceCategory": "游艺机",
        "ApprovalNumber": "GS-2009-1-161",
        "SupervisionPhone": "12318",
        "Link": "https://sh.gegia.cn/user/login.do#/detail/product-catalog?formListType=%E5%B7%B2%E9%80%9A%E8%BF%87%E4%BA%A7%E5%93%81%E7%9B%AE%E5%BD%95&id=his_1875&isChange=false&type=1"
      },
      {
        "Name": "恶灵手电筒",
        "DeviceCategory": "游艺机",
        "ApprovalNumber": "662",
        "SupervisionPhone": "12318",
        "Link": "https://sh.gegia.cn/user/login.do#/detail/product-catalog?formListType=%E5%B7%B2%E9%80%9A%E8%BF%87%E4%BA%A7%E5%93%81%E7%9B%AE%E5%BD%95&id=his_2428&isChange=false&type=1"
      },
      {
        "Name": "韵律世界（单人版）",
        "DeviceCategory": "游艺机",
        "ApprovalNumber": "110",
        "SupervisionPhone": "12318",
        "Link": "https://sh.gegia.cn/user/login.do#/detail/product-catalog?formListType=%E5%B7%B2%E9%80%9A%E8%BF%87%E4%BA%A7%E5%93%81%E7%9B%AE%E5%BD%95&id=his_2294&isChange=false&type=1"
      },
      {
        "Name": "盒子世界",
        "DeviceCategory": "游艺机",
        "ApprovalNumber": "5",
        "SupervisionPhone": "12318",
        "Link": "https://sh.gegia.cn/user/login.do#/detail/product-catalog?formListType=%E5%B7%B2%E9%80%9A%E8%BF%87%E4%BA%A7%E5%93%81%E7%9B%AE%E5%BD%95&id=his_2298&isChange=false&type=1"
      },
      {
        "Name": "全民叉鱼双人竖屏版",
        "DeviceCategory": "游艺机",
        "ApprovalNumber": "722",
        "SupervisionPhone": "12318",
        "Link": "https://sh.gegia.cn/user/login.do#/detail/product-catalog?formListType=%E5%B7%B2%E9%80%9A%E8%BF%87%E4%BA%A7%E5%93%81%E7%9B%AE%E5%BD%95&id=his_1554&isChange=false&type=1"
      },
      {
        "Name": "三国演武（双人豪华版）",
        "DeviceCategory": "游艺机",
        "ApprovalNumber": "556",
        "SupervisionPhone": "12318",
        "Link": "https://sh.gegia.cn/user/login.do#/detail/product-catalog?formListType=%E5%B7%B2%E9%80%9A%E8%BF%87%E4%BA%A7%E5%93%81%E7%9B%AE%E5%BD%95&id=his_2371&isChange=false&type=1"
      },
      {
        "Name": "拯救大英雄",
        "DeviceCategory": "游艺机",
        "ApprovalNumber": "38",
        "SupervisionPhone": "12318",
        "Link": "https://sh.gegia.cn/user/login.do#/detail/product-catalog?formListType=%E5%B7%B2%E9%80%9A%E8%BF%87%E4%BA%A7%E5%93%81%E7%9B%AE%E5%BD%95&id=his_2242&isChange=false&type=1"
      },
      {
        "Name": "玩具飞车",
        "DeviceCategory": "游艺机",
        "ApprovalNumber": "661",
        "SupervisionPhone": "12318",
        "Link": "https://sh.gegia.cn/user/login.do#/detail/product-catalog?formListType=%E5%B7%B2%E9%80%9A%E8%BF%87%E4%BA%A7%E5%93%81%E7%9B%AE%E5%BD%95&id=his_2427&isChange=false&type=1"
      },
      {
        "Name": "音乐弹球-双子",
        "DeviceCategory": "游艺机",
        "ApprovalNumber": "109",
        "SupervisionPhone": "12318",
        "Link": "https://sh.gegia.cn/user/login.do#/detail/product-catalog?formListType=%E5%B7%B2%E9%80%9A%E8%BF%87%E4%BA%A7%E5%93%81%E7%9B%AE%E5%BD%95&id=his_2293&isChange=false&type=1"
      },
      {
        "Name": "三国演武（单人版）",
        "DeviceCategory": "游艺机",
        "ApprovalNumber": "4",
        "SupervisionPhone": "12318",
        "Link": "https://sh.gegia.cn/user/login.do#/detail/product-catalog?formListType=%E5%B7%B2%E9%80%9A%E8%BF%87%E4%BA%A7%E5%93%81%E7%9B%AE%E5%BD%95&id=his_2297&isChange=false&type=1"
      },
      {
        "Name": "哇哇总动员",
        "DeviceCategory": "游艺机",
        "ApprovalNumber": "8",
        "SupervisionPhone": "12318",
        "Link": "https://sh.gegia.cn/user/login.do#/detail/product-catalog?formListType=%E5%B7%B2%E9%80%9A%E8%BF%87%E4%BA%A7%E5%93%81%E7%9B%AE%E5%BD%95&id=his_2301&isChange=false&type=1"
      },
      {
        "Name": "敲击棒棒团2",
        "DeviceCategory": "游艺机",
        "ApprovalNumber": "719",
        "SupervisionPhone": "12318",
        "Link": "https://sh.gegia.cn/user/login.do#/detail/product-catalog?formListType=%E5%B7%B2%E9%80%9A%E8%BF%87%E4%BA%A7%E5%93%81%E7%9B%AE%E5%BD%95&id=his_1549&isChange=false&type=1"
      },
      {
        "Name": "馋嘴宝贝",
        "DeviceCategory": "游艺机",
        "ApprovalNumber": "721",
        "SupervisionPhone": "12318",
        "Link": "https://sh.gegia.cn/user/login.do#/detail/product-catalog?formListType=%E5%B7%B2%E9%80%9A%E8%BF%87%E4%BA%A7%E5%93%81%E7%9B%AE%E5%BD%95&id=his_1553&isChange=false&type=1"
      },
      {
        "Name": "萌牛哆唻咪",
        "DeviceCategory": "游艺机",
        "ApprovalNumber": "725",
        "SupervisionPhone": "12318",
        "Link": "https://sh.gegia.cn/user/login.do#/detail/product-catalog?formListType=%E5%B7%B2%E9%80%9A%E8%BF%87%E4%BA%A7%E5%93%81%E7%9B%AE%E5%BD%95&id=his_1557&isChange=false&type=1"
      },
      {
        "Name": "三国演武",
        "DeviceCategory": "游艺机",
        "ApprovalNumber": "37",
        "SupervisionPhone": "12318",
        "Link": "https://sh.gegia.cn/user/login.do#/detail/product-catalog?formListType=%E5%B7%B2%E9%80%9A%E8%BF%87%E4%BA%A7%E5%93%81%E7%9B%AE%E5%BD%95&id=his_2241&isChange=false&type=1"
      },
      {
        "Name": "战龙传说",
        "DeviceCategory": "游艺机",
        "ApprovalNumber": "41",
        "SupervisionPhone": "12318",
        "Link": "https://sh.gegia.cn/user/login.do#/detail/product-catalog?formListType=%E5%B7%B2%E9%80%9A%E8%BF%87%E4%BA%A7%E5%93%81%E7%9B%AE%E5%BD%95&id=his_2245&isChange=false&type=1"
      },
      {
        "Name": "三国演武",
        "DeviceCategory": "游艺机",
        "ApprovalNumber": "108",
        "SupervisionPhone": "12318",
        "Link": "https://sh.gegia.cn/user/login.do#/detail/product-catalog?formListType=%E5%B7%B2%E9%80%9A%E8%BF%87%E4%BA%A7%E5%93%81%E7%9B%AE%E5%BD%95&id=his_2292&isChange=false&type=1"
      },
      {
        "Name": "炫次方（单机精装版）",
        "DeviceCategory": "游艺机",
        "ApprovalNumber": "112",
        "SupervisionPhone": "12318",
        "Link": "https://sh.gegia.cn/user/login.do#/detail/product-catalog?formListType=%E5%B7%B2%E9%80%9A%E8%BF%87%E4%BA%A7%E5%93%81%E7%9B%AE%E5%BD%95&id=his_2296&isChange=false&type=1"
      },
      {
        "Name": "疯狂大灌篮",
        "DeviceCategory": "游艺机",
        "ApprovalNumber": "7",
        "SupervisionPhone": "12318",
        "Link": "https://sh.gegia.cn/user/login.do#/detail/product-catalog?formListType=%E5%B7%B2%E9%80%9A%E8%BF%87%E4%BA%A7%E5%93%81%E7%9B%AE%E5%BD%95&id=his_2300&isChange=false&type=1"
      },
      {
        "Name": "动物笨猪跳",
        "DeviceCategory": "游艺机",
        "ApprovalNumber": "718",
        "SupervisionPhone": "12318",
        "Link": "https://sh.gegia.cn/user/login.do#/detail/product-catalog?formListType=%E5%B7%B2%E9%80%9A%E8%BF%87%E4%BA%A7%E5%93%81%E7%9B%AE%E5%BD%95&id=his_1548&isChange=false&type=1"
      },
      {
        "Name": "萌宝特攻",
        "DeviceCategory": "游艺机",
        "ApprovalNumber": "720",
        "SupervisionPhone": "12318",
        "Link": "https://sh.gegia.cn/user/login.do#/detail/product-catalog?formListType=%E5%B7%B2%E9%80%9A%E8%BF%87%E4%BA%A7%E5%93%81%E7%9B%AE%E5%BD%95&id=his_1552&isChange=false&type=1"
      },
      {
        "Name": "玩具Q车",
        "DeviceCategory": "游艺机",
        "ApprovalNumber": "724",
        "SupervisionPhone": "12318",
        "Link": "https://sh.gegia.cn/user/login.do#/detail/product-catalog?formListType=%E5%B7%B2%E9%80%9A%E8%BF%87%E4%BA%A7%E5%93%81%E7%9B%AE%E5%BD%95&id=his_1556&isChange=false&type=1"
      },
      {
        "Name": "巅峰4D魔幻穿梭（2人版）",
        "DeviceCategory": "游艺机",
        "ApprovalNumber": "36",
        "SupervisionPhone": "12318",
        "Link": "https://sh.gegia.cn/user/login.do#/detail/product-catalog?formListType=%E5%B7%B2%E9%80%9A%E8%BF%87%E4%BA%A7%E5%93%81%E7%9B%AE%E5%BD%95&id=his_2240&isChange=false&type=1"
      },
      {
        "Name": "音域对抗",
        "DeviceCategory": "游艺机",
        "ApprovalNumber": "40",
        "SupervisionPhone": "12318",
        "Link": "https://sh.gegia.cn/user/login.do#/detail/product-catalog?formListType=%E5%B7%B2%E9%80%9A%E8%BF%87%E4%BA%A7%E5%93%81%E7%9B%AE%E5%BD%95&id=his_2244&isChange=false&type=1"
      },
      {
        "Name": "音乐弹球",
        "DeviceCategory": "游艺机",
        "ApprovalNumber": "111",
        "SupervisionPhone": "12318",
        "Link": "https://sh.gegia.cn/user/login.do#/detail/product-catalog?formListType=%E5%B7%B2%E9%80%9A%E8%BF%87%E4%BA%A7%E5%93%81%E7%9B%AE%E5%BD%95&id=his_2295&isChange=false&type=1"
      },
      {
        "Name": "玩偶魔方2",
        "DeviceCategory": "游艺机",
        "ApprovalNumber": "6",
        "SupervisionPhone": "12318",
        "Link": "https://sh.gegia.cn/user/login.do#/detail/product-catalog?formListType=%E5%B7%B2%E9%80%9A%E8%BF%87%E4%BA%A7%E5%93%81%E7%9B%AE%E5%BD%95&id=his_2299&isChange=false&type=1"
      },
      {
        "Name": "哈皮小赛车",
        "DeviceCategory": "游艺机",
        "ApprovalNumber": "717",
        "SupervisionPhone": "12318",
        "Link": "https://sh.gegia.cn/user/login.do#/detail/product-catalog?formListType=%E5%B7%B2%E9%80%9A%E8%BF%87%E4%BA%A7%E5%93%81%E7%9B%AE%E5%BD%95&id=his_1547&isChange=false&type=1"
      },
      {
        "Name": "全明星篮球",
        "DeviceCategory": "游艺机",
        "ApprovalNumber": "723",
        "SupervisionPhone": "12318",
        "Link": "https://sh.gegia.cn/user/login.do#/detail/product-catalog?formListType=%E5%B7%B2%E9%80%9A%E8%BF%87%E4%BA%A7%E5%93%81%E7%9B%AE%E5%BD%95&id=his_1555&isChange=false&type=1"
      },
      {
        "Name": "希力指多星3",
        "DeviceCategory": "游艺机",
        "ApprovalNumber": "557",
        "SupervisionPhone": "12318",
        "Link": "https://sh.gegia.cn/user/login.do#/detail/product-catalog?formListType=%E5%B7%B2%E9%80%9A%E8%BF%87%E4%BA%A7%E5%93%81%E7%9B%AE%E5%BD%95&id=his_2372&isChange=false&type=1"
      },
      {
        "Name": "音乐连连看",
        "DeviceCategory": "游艺机",
        "ApprovalNumber": "39",
        "SupervisionPhone": "12318",
        "Link": "https://sh.gegia.cn/user/login.do#/detail/product-catalog?formListType=%E5%B7%B2%E9%80%9A%E8%BF%87%E4%BA%A7%E5%93%81%E7%9B%AE%E5%BD%95&id=his_2243&isChange=false&type=1"
      }
    ]
  }
]